{"1": {"Area [m2]": 285.41, "Mean Average Height [m]": 1.74, "Electricity [GJ]": 259.35, "Natural Gas [GJ]": 45.13, "Water [m3]": 15.94, "Lat": 41.867863, "Lon": -87.628662, "Weather Location Lat": 41.867863, "Weather Location Lon": -87.628662}, "10": {"Area [m2]": 282.49, "Mean Average Height [m]": 3.73, "Electricity [GJ]": 354.79, "Natural Gas [GJ]": 40.52, "Water [m3]": 15.77, "Lat": 41.86787, "Lon": -87.62640400000001, "Weather Location Lat": 41.86787, "Weather Location Lon": -87.62640400000001}, "100": {"Area [m2]": 42305.17, "Mean Average Height [m]": 63.84, "Electricity [GJ]": 13343.06, "Natural Gas [GJ]": 10366.43, "Water [m3]": 319863.59, "Lat": 41.870391999999995, "Lon": -87.630981, "Weather Location Lat": 41.870391999999995, "Weather Location Lon": -87.630981}, "101": {"Area [m2]": 9876.54, "Mean Average Height [m]": 46.53, "Electricity [GJ]": 5183.45, "Natural Gas [GJ]": 3666.26, "Water [m3]": 84247.17, "Lat": 41.870434, "Lon": -87.625275, "Weather Location Lat": 41.870434, "Weather Location Lon": -87.625275}, "10102": {"Area [m2]": 318953.75, "Mean Average Height [m]": 125.31, "Electricity [GJ]": 81218.16, "Natural Gas [GJ]": 54278.46, "Water [m3]": 1871203.16, "Lat": 41.880542999999996, "Lon": -87.637939, "Weather Location Lat": 41.880542999999996, "Weather Location Lon": -87.637939}, "10105": {"Area [m2]": 140599.95, "Mean Average Height [m]": 123.32, "Electricity [GJ]": 37497.9, "Natural Gas [GJ]": 27873.98, "Water [m3]": 872658.98, "Lat": 41.881393, "Lon": -87.63678, "Weather Location Lat": 41.881393, "Weather Location Lon": -87.63678}, "10108": {"Area [m2]": 57755.42, "Mean Average Height [m]": 30.27, "Electricity [GJ]": 16869.81, "Natural Gas [GJ]": 10622.87, "Water [m3]": 342603.88, "Lat": 41.881397, "Lon": -87.635651, "Weather Location Lat": 41.881397, "Weather Location Lon": -87.635651}, "10119": {"Area [m2]": 46754.14, "Mean Average Height [m]": 106.4, "Electricity [GJ]": 14518.16, "Natural Gas [GJ]": 12130.47, "Water [m3]": 365142.8, "Lat": 41.881397, "Lon": -87.635651, "Weather Location Lat": 41.881397, "Weather Location Lon": -87.635651}, "10121": {"Area [m2]": 129451.4, "Mean Average Height [m]": 155.9, "Electricity [GJ]": 34904.08, "Natural Gas [GJ]": 28358.64, "Water [m3]": 839007.79, "Lat": 41.881415999999994, "Lon": -87.633362, "Weather Location Lat": 41.881415999999994, "Weather Location Lon": -87.633362}, "10141": {"Area [m2]": 99586.96, "Mean Average Height [m]": 129.14, "Electricity [GJ]": 27504.3, "Natural Gas [GJ]": 21696.3, "Water [m3]": 661304.25, "Lat": 41.881415999999994, "Lon": -87.633362, "Weather Location Lat": 41.881415999999994, "Weather Location Lon": -87.633362}, "10151": {"Area [m2]": 25331.57, "Mean Average Height [m]": 45.31, "Electricity [GJ]": 8987.59, "Natural Gas [GJ]": 6002.86, "Water [m3]": 179288.36, "Lat": 41.881428, "Lon": -87.63110400000001, "Weather Location Lat": 41.881428, "Weather Location Lon": -87.63110400000001}, "10153": {"Area [m2]": 83576.04, "Mean Average Height [m]": 71.72, "Electricity [GJ]": 23343.77, "Natural Gas [GJ]": 16138.29, "Water [m3]": 519736.52, "Lat": 41.881423999999996, "Lon": -87.632233, "Weather Location Lat": 41.881423999999996, "Weather Location Lon": -87.632233}, "10157": {"Area [m2]": 283570.83, "Mean Average Height [m]": 171.1, "Electricity [GJ]": 72611.49, "Natural Gas [GJ]": 54597.33, "Water [m3]": 1667740.19, "Lat": 41.881428, "Lon": -87.63110400000001, "Weather Location Lat": 41.881428, "Weather Location Lon": -87.63110400000001}, "10182": {"Area [m2]": 62671.56, "Mean Average Height [m]": 38.32, "Electricity [GJ]": 18216.7, "Natural Gas [GJ]": 11887.91, "Water [m3]": 406740.83, "Lat": 41.880592, "Lon": -87.628815, "Weather Location Lat": 41.880592, "Weather Location Lon": -87.628815}, "10183": {"Area [m2]": 105737.46, "Mean Average Height [m]": 117.11, "Electricity [GJ]": 28953.65, "Natural Gas [GJ]": 21862.98, "Water [m3]": 680506.71, "Lat": 41.881443, "Lon": -87.628815, "Weather Location Lat": 41.881443, "Weather Location Lon": -87.628815}, "10231": {"Area [m2]": 200254.52, "Mean Average Height [m]": 50.16, "Electricity [GJ]": 51789.75, "Natural Gas [GJ]": 33718.83, "Water [m3]": 1124324.27, "Lat": 41.880604, "Lon": -87.627686, "Weather Location Lat": 41.880604, "Weather Location Lon": -87.627686}, "10250": {"Area [m2]": 40985.16, "Mean Average Height [m]": 79.17, "Electricity [GJ]": 12896.09, "Natural Gas [GJ]": 10013.21, "Water [m3]": 279036.96, "Lat": 41.881462, "Lon": -87.626526, "Weather Location Lat": 41.881462, "Weather Location Lon": -87.626526}, "10279": {"Area [m2]": 110945.16, "Mean Average Height [m]": 51.39, "Electricity [GJ]": 30121.29, "Natural Gas [GJ]": 21104.69, "Water [m3]": 686737.7, "Lat": 41.880615, "Lon": -87.62539699999999, "Weather Location Lat": 41.880615, "Weather Location Lon": -87.62539699999999}, "103": {"Area [m2]": 2087.29, "Mean Average Height [m]": 7.11, "Electricity [GJ]": 1459.2, "Natural Gas [GJ]": 51.0, "Water [m3]": 116.55, "Lat": 41.870365, "Lon": -87.637817, "Weather Location Lat": 41.870365, "Weather Location Lon": -87.637817}, "104": {"Area [m2]": 20472.32, "Mean Average Height [m]": 41.21, "Electricity [GJ]": 7808.67, "Natural Gas [GJ]": 5191.21, "Water [m3]": 142793.95, "Lat": 41.870407, "Lon": -87.628723, "Weather Location Lat": 41.870407, "Weather Location Lon": -87.628723}, "105": {"Area [m2]": 49959.61, "Mean Average Height [m]": 44.19, "Electricity [GJ]": 15054.6, "Natural Gas [GJ]": 9915.52, "Water [m3]": 323936.55, "Lat": 41.870422, "Lon": -87.626434, "Weather Location Lat": 41.870422, "Weather Location Lon": -87.626434}, "10858": {"Area [m2]": 3192.38, "Mean Average Height [m]": 11.18, "Electricity [GJ]": 2245.14, "Natural Gas [GJ]": 58.92, "Water [m3]": 178.25, "Lat": 41.881462, "Lon": -87.626526, "Weather Location Lat": 41.881462, "Weather Location Lon": -87.626526}, "109": {"Area [m2]": 2827.05, "Mean Average Height [m]": 10.94, "Electricity [GJ]": 1533.03, "Natural Gas [GJ]": 92.88, "Water [m3]": 157.85, "Lat": 41.87122, "Lon": -87.635559, "Weather Location Lat": 41.87122, "Weather Location Lon": -87.635559}, "10951": {"Area [m2]": 56931.09, "Mean Average Height [m]": 102.52, "Electricity [GJ]": 16955.46, "Natural Gas [GJ]": 13332.39, "Water [m3]": 406483.08, "Lat": 41.882275, "Lon": -87.632263, "Weather Location Lat": 41.882275, "Weather Location Lon": -87.632263}, "10952": {"Area [m2]": 190733.77, "Mean Average Height [m]": 114.96, "Electricity [GJ]": 49690.93, "Natural Gas [GJ]": 35764.63, "Water [m3]": 1122464.0, "Lat": 41.882286, "Lon": -87.63110400000001, "Weather Location Lat": 41.882286, "Weather Location Lon": -87.63110400000001}, "10953": {"Area [m2]": 127012.85, "Mean Average Height [m]": 80.56, "Electricity [GJ]": 33984.24, "Natural Gas [GJ]": 23991.92, "Water [m3]": 752701.56, "Lat": 41.882290000000005, "Lon": -87.628845, "Weather Location Lat": 41.882290000000005, "Weather Location Lon": -87.628845}, "10954": {"Area [m2]": 121372.19, "Mean Average Height [m]": 147.32, "Electricity [GJ]": 32896.9, "Natural Gas [GJ]": 26542.9, "Water [m3]": 789887.2, "Lat": 41.882271, "Lon": -87.63452099999999, "Weather Location Lat": 41.882271, "Weather Location Lon": -87.63452099999999}, "10955": {"Area [m2]": 69136.61, "Mean Average Height [m]": 60.44, "Electricity [GJ]": 19759.55, "Natural Gas [GJ]": 13510.03, "Water [m3]": 427744.28, "Lat": 41.882275, "Lon": -87.632263, "Weather Location Lat": 41.882275, "Weather Location Lon": -87.632263}, "10957": {"Area [m2]": 86718.57, "Mean Average Height [m]": 137.72, "Electricity [GJ]": 24398.27, "Natural Gas [GJ]": 19949.86, "Water [m3]": 603205.88, "Lat": 41.882256, "Lon": -87.635681, "Weather Location Lat": 41.882256, "Weather Location Lon": -87.635681}, "10967": {"Area [m2]": 195468.37, "Mean Average Height [m]": 148.39, "Electricity [GJ]": 51001.05, "Natural Gas [GJ]": 39070.78, "Water [m3]": 1179785.09, "Lat": 41.882244, "Lon": -87.63681, "Weather Location Lat": 41.882244, "Weather Location Lon": -87.63681}, "11": {"Area [m2]": 754.84, "Mean Average Height [m]": 8.94, "Electricity [GJ]": 597.03, "Natural Gas [GJ]": 45.99, "Water [m3]": 42.15, "Lat": 41.867859, "Lon": -87.62982199999999, "Weather Location Lat": 41.867859, "Weather Location Lon": -87.62982199999999}, "110": {"Area [m2]": 5710.31, "Mean Average Height [m]": 5.42, "Electricity [GJ]": 2732.18, "Natural Gas [GJ]": 220.54, "Water [m3]": 318.85, "Lat": 41.870399, "Lon": -87.629852, "Weather Location Lat": 41.870399, "Weather Location Lon": -87.629852}, "11140": {"Area [m2]": 280.99, "Mean Average Height [m]": 5.01, "Electricity [GJ]": 304.32, "Natural Gas [GJ]": 41.73, "Water [m3]": 15.69, "Lat": 41.882290000000005, "Lon": -87.629974, "Weather Location Lat": 41.882290000000005, "Weather Location Lon": -87.629974}, "113": {"Area [m2]": 80254.33, "Mean Average Height [m]": 45.35, "Electricity [GJ]": 22567.03, "Natural Gas [GJ]": 14828.48, "Water [m3]": 514987.4, "Lat": 41.870419, "Lon": -87.627563, "Weather Location Lat": 41.870419, "Weather Location Lon": -87.627563}, "114": {"Area [m2]": 43059.35, "Mean Average Height [m]": 52.12, "Electricity [GJ]": 13354.23, "Natural Gas [GJ]": 8848.87, "Water [m3]": 282818.71, "Lat": 41.871277, "Lon": -87.626434, "Weather Location Lat": 41.871277, "Weather Location Lon": -87.626434}, "11484": {"Area [m2]": 3221.58, "Mean Average Height [m]": 11.57, "Electricity [GJ]": 2144.17, "Natural Gas [GJ]": 64.14, "Water [m3]": 179.88, "Lat": 41.882275, "Lon": -87.633392, "Weather Location Lat": 41.882275, "Weather Location Lon": -87.633392}, "115": {"Area [m2]": 18515.21, "Mean Average Height [m]": 14.39, "Electricity [GJ]": 6150.44, "Natural Gas [GJ]": 1230.96, "Water [m3]": 1033.84, "Lat": 41.871277, "Lon": -87.62530500000001, "Weather Location Lat": 41.871277, "Weather Location Lon": -87.62530500000001}, "11550": {"Area [m2]": 124467.94, "Mean Average Height [m]": 145.67, "Electricity [GJ]": 33594.2, "Natural Gas [GJ]": 26145.92, "Water [m3]": 792342.36, "Lat": 41.882275, "Lon": -87.633392, "Weather Location Lat": 41.882275, "Weather Location Lon": -87.633392}, "11581": {"Area [m2]": 96930.51, "Mean Average Height [m]": 54.52, "Electricity [GJ]": 26612.79, "Natural Gas [GJ]": 17626.49, "Water [m3]": 591665.01, "Lat": 41.882305, "Lon": -87.62539699999999, "Weather Location Lat": 41.882305, "Weather Location Lon": -87.62539699999999}, "11586": {"Area [m2]": 98999.61, "Mean Average Height [m]": 57.52, "Electricity [GJ]": 27137.02, "Natural Gas [GJ]": 18124.68, "Water [m3]": 608170.45, "Lat": 41.882305, "Lon": -87.62539699999999, "Weather Location Lat": 41.882305, "Weather Location Lon": -87.62539699999999}, "116": {"Area [m2]": 42354.27, "Mean Average Height [m]": 27.04, "Electricity [GJ]": 13714.28, "Natural Gas [GJ]": 2833.94, "Water [m3]": 2364.94, "Lat": 41.871277, "Lon": -87.62530500000001, "Weather Location Lat": 41.871277, "Weather Location Lon": -87.62530500000001}, "11606": {"Area [m2]": 224363.03, "Mean Average Height [m]": 64.66, "Electricity [GJ]": 57765.52, "Natural Gas [GJ]": 38830.46, "Water [m3]": 1268843.19, "Lat": 41.882294, "Lon": -87.627686, "Weather Location Lat": 41.882294, "Weather Location Lon": -87.627686}, "11608": {"Area [m2]": 99566.99, "Mean Average Height [m]": 110.35, "Electricity [GJ]": 27409.08, "Natural Gas [GJ]": 20910.2, "Water [m3]": 638027.44, "Lat": 41.882290000000005, "Lon": -87.629974, "Weather Location Lat": 41.882290000000005, "Weather Location Lon": -87.629974}, "11619": {"Area [m2]": 85582.76, "Mean Average Height [m]": 46.25, "Electricity [GJ]": 23744.18, "Natural Gas [GJ]": 16189.23, "Water [m3]": 505367.61, "Lat": 41.882290000000005, "Lon": -87.628845, "Weather Location Lat": 41.882290000000005, "Weather Location Lon": -87.628845}, "11632": {"Area [m2]": 141825.49, "Mean Average Height [m]": 76.62, "Electricity [GJ]": 37601.06, "Natural Gas [GJ]": 26195.15, "Water [m3]": 831620.54, "Lat": 41.882275, "Lon": -87.632263, "Weather Location Lat": 41.882275, "Weather Location Lon": -87.632263}, "11634": {"Area [m2]": 71381.0, "Mean Average Height [m]": 112.93, "Electricity [GJ]": 20525.32, "Natural Gas [GJ]": 16261.46, "Water [m3]": 491333.7, "Lat": 41.882256, "Lon": -87.635681, "Weather Location Lat": 41.882256, "Weather Location Lon": -87.635681}, "11637": {"Area [m2]": 140876.45, "Mean Average Height [m]": 54.81, "Electricity [GJ]": 37462.79, "Natural Gas [GJ]": 27486.57, "Water [m3]": 846481.69, "Lat": 41.882275, "Lon": -87.633392, "Weather Location Lat": 41.882275, "Weather Location Lon": -87.633392}, "11640": {"Area [m2]": 37398.57, "Mean Average Height [m]": 79.5, "Electricity [GJ]": 12107.98, "Natural Gas [GJ]": 9371.2, "Water [m3]": 284536.09, "Lat": 41.882286, "Lon": -87.63110400000001, "Weather Location Lat": 41.882286, "Weather Location Lon": -87.63110400000001}, "11677": {"Area [m2]": 208116.18, "Mean Average Height [m]": 86.31, "Electricity [GJ]": 53984.22, "Natural Gas [GJ]": 36206.87, "Water [m3]": 1241379.51, "Lat": 41.88224, "Lon": -87.637939, "Weather Location Lat": 41.88224, "Weather Location Lon": -87.637939}, "11678": {"Area [m2]": 16613.54, "Mean Average Height [m]": 37.59, "Electricity [GJ]": 6916.0, "Natural Gas [GJ]": 4285.57, "Water [m3]": 134094.99, "Lat": 41.882244, "Lon": -87.63681, "Weather Location Lat": 41.882244, "Weather Location Lon": -87.63681}, "11682": {"Area [m2]": 74513.09, "Mean Average Height [m]": 67.91, "Electricity [GJ]": 21145.1, "Natural Gas [GJ]": 15533.49, "Water [m3]": 472735.61, "Lat": 41.882244, "Lon": -87.63681, "Weather Location Lat": 41.882244, "Weather Location Lon": -87.63681}, "11851": {"Area [m2]": 122.03, "Mean Average Height [m]": 5.99, "Electricity [GJ]": 252.2, "Natural Gas [GJ]": 40.35, "Water [m3]": 6.81, "Lat": 41.883156, "Lon": -87.62655600000001, "Weather Location Lat": 41.883156, "Weather Location Lon": -87.62655600000001}, "11967": {"Area [m2]": 148.19, "Mean Average Height [m]": 4.22, "Electricity [GJ]": 281.51, "Natural Gas [GJ]": 40.32, "Water [m3]": 8.27, "Lat": 41.883133, "Lon": -87.629974, "Weather Location Lat": 41.883133, "Weather Location Lon": -87.629974}, "12": {"Area [m2]": 754.84, "Mean Average Height [m]": 8.66, "Electricity [GJ]": 585.84, "Natural Gas [GJ]": 46.6, "Water [m3]": 42.15, "Lat": 41.867863, "Lon": -87.628662, "Weather Location Lat": 41.867863, "Weather Location Lon": -87.628662}, "12017": {"Area [m2]": 193.29, "Mean Average Height [m]": 2.79, "Electricity [GJ]": 250.02, "Natural Gas [GJ]": 40.96, "Water [m3]": 10.79, "Lat": 41.883133, "Lon": -87.629974, "Weather Location Lat": 41.883133, "Weather Location Lon": -87.629974}, "121": {"Area [m2]": 14006.31, "Mean Average Height [m]": 21.44, "Electricity [GJ]": 6028.53, "Natural Gas [GJ]": 637.05, "Water [m3]": 782.07, "Lat": 41.871254, "Lon": -87.629852, "Weather Location Lat": 41.871254, "Weather Location Lon": -87.629852}, "122": {"Area [m2]": 107087.96, "Mean Average Height [m]": 26.98, "Electricity [GJ]": 32335.11, "Natural Gas [GJ]": 7437.76, "Water [m3]": 5979.48, "Lat": 41.870377000000005, "Lon": -87.634399, "Weather Location Lat": 41.870377000000005, "Weather Location Lon": -87.634399}, "123": {"Area [m2]": 17997.97, "Mean Average Height [m]": 39.19, "Electricity [GJ]": 7220.81, "Natural Gas [GJ]": 4318.67, "Water [m3]": 132405.95, "Lat": 41.872078, "Lon": -87.633301, "Weather Location Lat": 41.872078, "Weather Location Lon": -87.633301}, "12377": {"Area [m2]": 139.38, "Mean Average Height [m]": 3.39, "Electricity [GJ]": 260.05, "Natural Gas [GJ]": 40.33, "Water [m3]": 7.78, "Lat": 41.883133, "Lon": -87.629974, "Weather Location Lat": 41.883133, "Weather Location Lon": -87.629974}, "124": {"Area [m2]": 29402.38, "Mean Average Height [m]": 21.03, "Electricity [GJ]": 12354.81, "Natural Gas [GJ]": 1335.46, "Water [m3]": 1641.74, "Lat": 41.871258000000005, "Lon": -87.628723, "Weather Location Lat": 41.871258000000005, "Weather Location Lon": -87.628723}, "125": {"Area [m2]": 15654.25, "Mean Average Height [m]": 10.49, "Electricity [GJ]": 5607.07, "Natural Gas [GJ]": 943.21, "Water [m3]": 874.09, "Lat": 41.871254, "Lon": -87.629852, "Weather Location Lat": 41.871254, "Weather Location Lon": -87.629852}, "12571": {"Area [m2]": 107374.93, "Mean Average Height [m]": 65.67, "Electricity [GJ]": 29283.26, "Natural Gas [GJ]": 24911.35, "Water [m3]": 658191.82, "Lat": 41.883114, "Lon": -87.633392, "Weather Location Lat": 41.883114, "Weather Location Lon": -87.633392}, "12579": {"Area [m2]": 822.41, "Mean Average Height [m]": 3.13, "Electricity [GJ]": 648.08, "Natural Gas [GJ]": 45.36, "Water [m3]": 45.92, "Lat": 41.883990999999995, "Lon": -87.629974, "Weather Location Lat": 41.883990999999995, "Weather Location Lon": -87.629974}, "12584": {"Area [m2]": 600.72, "Mean Average Height [m]": 2.82, "Electricity [GJ]": 449.47, "Natural Gas [GJ]": 46.99, "Water [m3]": 33.54, "Lat": 41.883984000000005, "Lon": -87.631134, "Weather Location Lat": 41.883984000000005, "Weather Location Lon": -87.631134}, "12593": {"Area [m2]": 107576.88, "Mean Average Height [m]": 56.73, "Electricity [GJ]": 29143.34, "Natural Gas [GJ]": 19733.74, "Water [m3]": 630159.44, "Lat": 41.883095000000004, "Lon": -87.635681, "Weather Location Lat": 41.883095000000004, "Weather Location Lon": -87.635681}, "126": {"Area [m2]": 615.25, "Mean Average Height [m]": 11.66, "Electricity [GJ]": 563.02, "Natural Gas [GJ]": 42.51, "Water [m3]": 34.35, "Lat": 41.872063, "Lon": -87.636719, "Weather Location Lat": 41.872063, "Weather Location Lon": -87.636719}, "12604": {"Area [m2]": 76629.56, "Mean Average Height [m]": 87.59, "Electricity [GJ]": 21715.48, "Natural Gas [GJ]": 15776.72, "Water [m3]": 498494.56, "Lat": 41.883095000000004, "Lon": -87.63681, "Weather Location Lat": 41.883095000000004, "Weather Location Lon": -87.63681}, "131": {"Area [m2]": 16993.83, "Mean Average Height [m]": 52.82, "Electricity [GJ]": 7051.99, "Natural Gas [GJ]": 838.52, "Water [m3]": 948.89, "Lat": 41.872078, "Lon": -87.633301, "Weather Location Lat": 41.872078, "Weather Location Lon": -87.633301}, "13129": {"Area [m2]": 226461.59, "Mean Average Height [m]": 177.85, "Electricity [GJ]": 58653.76, "Natural Gas [GJ]": 45019.2, "Water [m3]": 1356552.53, "Lat": 41.883984000000005, "Lon": -87.631134, "Weather Location Lat": 41.883984000000005, "Weather Location Lon": -87.631134}, "13173": {"Area [m2]": 117565.58, "Mean Average Height [m]": 123.43, "Electricity [GJ]": 31826.4, "Natural Gas [GJ]": 24239.95, "Water [m3]": 735664.79, "Lat": 41.883953000000005, "Lon": -87.635681, "Weather Location Lat": 41.883953000000005, "Weather Location Lon": -87.635681}, "132": {"Area [m2]": 11906.07, "Mean Average Height [m]": 35.93, "Electricity [GJ]": 4831.44, "Natural Gas [GJ]": 609.29, "Water [m3]": 664.8, "Lat": 41.872093, "Lon": -87.631012, "Weather Location Lat": 41.872093, "Weather Location Lon": -87.631012}, "13200": {"Area [m2]": 194906.56, "Mean Average Height [m]": 51.61, "Electricity [GJ]": 50423.41, "Natural Gas [GJ]": 30725.37, "Water [m3]": 1085587.08, "Lat": 41.883117999999996, "Lon": -87.632263, "Weather Location Lat": 41.883117999999996, "Weather Location Lon": -87.632263}, "13202": {"Area [m2]": 45381.44, "Mean Average Height [m]": 24.74, "Electricity [GJ]": 14776.72, "Natural Gas [GJ]": 3041.25, "Water [m3]": 2533.97, "Lat": 41.883163, "Lon": -87.625427, "Weather Location Lat": 41.883163, "Weather Location Lon": -87.625427}, "13206": {"Area [m2]": 176447.4, "Mean Average Height [m]": 92.04, "Electricity [GJ]": 46310.76, "Natural Gas [GJ]": 32351.99, "Water [m3]": 1074963.75, "Lat": 41.883156, "Lon": -87.62655600000001, "Weather Location Lat": 41.883156, "Weather Location Lon": -87.62655600000001}, "13227": {"Area [m2]": 27380.62, "Mean Average Height [m]": 56.09, "Electricity [GJ]": 9555.86, "Natural Gas [GJ]": 6713.24, "Water [m3]": 206585.11, "Lat": 41.883957, "Lon": -87.634552, "Weather Location Lat": 41.883957, "Weather Location Lon": -87.634552}, "13231": {"Area [m2]": 75503.21, "Mean Average Height [m]": 112.47, "Electricity [GJ]": 21554.83, "Natural Gas [GJ]": 17080.8, "Water [m3]": 518840.5, "Lat": 41.883942, "Lon": -87.636841, "Weather Location Lat": 41.883942, "Weather Location Lon": -87.636841}, "13244": {"Area [m2]": 141519.49, "Mean Average Height [m]": 33.96, "Electricity [GJ]": 37348.31, "Natural Gas [GJ]": 23479.84, "Water [m3]": 789810.11, "Lat": 41.883144, "Lon": -87.628845, "Weather Location Lat": 41.883144, "Weather Location Lon": -87.628845}, "13255": {"Area [m2]": 266788.33, "Mean Average Height [m]": 62.17, "Electricity [GJ]": 68003.03, "Natural Gas [GJ]": 42229.2, "Water [m3]": 1466244.01, "Lat": 41.883148, "Lon": -87.627686, "Weather Location Lat": 41.883148, "Weather Location Lon": -87.627686}, "13263": {"Area [m2]": 80739.09, "Mean Average Height [m]": 44.73, "Electricity [GJ]": 22527.45, "Natural Gas [GJ]": 14938.48, "Water [m3]": 472648.12, "Lat": 41.883965, "Lon": -87.633423, "Weather Location Lat": 41.883965, "Weather Location Lon": -87.633423}, "133": {"Area [m2]": 403.84, "Mean Average Height [m]": 8.22, "Electricity [GJ]": 469.49, "Natural Gas [GJ]": 40.73, "Water [m3]": 22.55, "Lat": 41.872085999999996, "Lon": -87.632141, "Weather Location Lat": 41.872085999999996, "Weather Location Lon": -87.632141}, "13565": {"Area [m2]": 153.58, "Mean Average Height [m]": 4.33, "Electricity [GJ]": 291.42, "Natural Gas [GJ]": 40.32, "Water [m3]": 8.58, "Lat": 41.884865000000005, "Lon": -87.624298, "Weather Location Lat": 41.884865000000005, "Weather Location Lon": -87.624298}, "13767": {"Area [m2]": 2684.71, "Mean Average Height [m]": 8.74, "Electricity [GJ]": 1231.85, "Natural Gas [GJ]": 138.37, "Water [m3]": 149.91, "Lat": 41.8848, "Lon": -87.635681, "Weather Location Lat": 41.8848, "Weather Location Lon": -87.635681}, "13909": {"Area [m2]": 76722.15, "Mean Average Height [m]": 134.7, "Electricity [GJ]": 21866.83, "Natural Gas [GJ]": 18421.73, "Water [m3]": 520455.51, "Lat": 41.884861, "Lon": -87.625427, "Weather Location Lat": 41.884861, "Weather Location Lon": -87.625427}, "13987": {"Area [m2]": 19972.67, "Mean Average Height [m]": 16.15, "Electricity [GJ]": 6751.84, "Natural Gas [GJ]": 1319.65, "Water [m3]": 1115.22, "Lat": 41.884857000000004, "Lon": -87.626587, "Weather Location Lat": 41.884857000000004, "Weather Location Lon": -87.626587}, "14": {"Area [m2]": 5975.49, "Mean Average Height [m]": 17.77, "Electricity [GJ]": 2527.46, "Natural Gas [GJ]": 294.05, "Water [m3]": 333.65, "Lat": 41.86787, "Lon": -87.62640400000001, "Weather Location Lat": 41.86787, "Weather Location Lon": -87.62640400000001}, "14004": {"Area [m2]": 57234.8, "Mean Average Height [m]": 75.17, "Electricity [GJ]": 16894.33, "Natural Gas [GJ]": 12092.73, "Water [m3]": 374099.31, "Lat": 41.884811, "Lon": -87.633423, "Weather Location Lat": 41.884811, "Weather Location Lon": -87.633423}, "14037": {"Area [m2]": 100286.42, "Mean Average Height [m]": 51.18, "Electricity [GJ]": 27321.06, "Natural Gas [GJ]": 18122.93, "Water [m3]": 578400.98, "Lat": 41.884846, "Lon": -87.628845, "Weather Location Lat": 41.884846, "Weather Location Lon": -87.628845}, "14054": {"Area [m2]": 6329.02, "Mean Average Height [m]": 22.4, "Electricity [GJ]": 2771.06, "Natural Gas [GJ]": 296.58, "Water [m3]": 353.39, "Lat": 41.8848, "Lon": -87.635681, "Weather Location Lat": 41.8848, "Weather Location Lon": -87.635681}, "14056": {"Area [m2]": 16107.7, "Mean Average Height [m]": 18.29, "Electricity [GJ]": 5632.08, "Natural Gas [GJ]": 1024.66, "Water [m3]": 899.41, "Lat": 41.884803999999995, "Lon": -87.634552, "Weather Location Lat": 41.884803999999995, "Weather Location Lon": -87.634552}, "14058": {"Area [m2]": 174058.1, "Mean Average Height [m]": 138.96, "Electricity [GJ]": 45713.0, "Natural Gas [GJ]": 33829.61, "Water [m3]": 1054042.7, "Lat": 41.8848, "Lon": -87.636841, "Weather Location Lat": 41.8848, "Weather Location Lon": -87.636841}, "141": {"Area [m2]": 40090.55, "Mean Average Height [m]": 32.22, "Electricity [GJ]": 12601.11, "Natural Gas [GJ]": 7953.7, "Water [m3]": 259944.45, "Lat": 41.872108000000004, "Lon": -87.62759399999999, "Weather Location Lat": 41.872108000000004, "Weather Location Lon": -87.62759399999999}, "14256": {"Area [m2]": 148.11, "Mean Average Height [m]": 2.92, "Electricity [GJ]": 238.76, "Natural Gas [GJ]": 40.53, "Water [m3]": 8.27, "Lat": 41.8857, "Lon": -87.626587, "Weather Location Lat": 41.8857, "Weather Location Lon": -87.626587}, "14389": {"Area [m2]": 1464.03, "Mean Average Height [m]": 8.46, "Electricity [GJ]": 1191.62, "Natural Gas [GJ]": 43.5, "Water [m3]": 81.75, "Lat": 41.884811, "Lon": -87.633423, "Weather Location Lat": 41.884811, "Weather Location Lon": -87.633423}, "14398": {"Area [m2]": 1215.48, "Mean Average Height [m]": 9.67, "Electricity [GJ]": 1255.85, "Natural Gas [GJ]": 40.95, "Water [m3]": 67.87, "Lat": 41.884811, "Lon": -87.633423, "Weather Location Lat": 41.884811, "Weather Location Lon": -87.633423}, "1449": {"Area [m2]": 4516.65, "Mean Average Height [m]": 30.61, "Electricity [GJ]": 3787.81, "Natural Gas [GJ]": 1712.59, "Water [m3]": 39439.54, "Lat": 41.875481, "Lon": -87.633301, "Weather Location Lat": 41.875481, "Weather Location Lon": -87.633301}, "14669": {"Area [m2]": 35461.75, "Mean Average Height [m]": 35.44, "Electricity [GJ]": 11435.59, "Natural Gas [GJ]": 7456.64, "Water [m3]": 223290.46, "Lat": 41.884861, "Lon": -87.625427, "Weather Location Lat": 41.884861, "Weather Location Lon": -87.625427}, "14692": {"Area [m2]": 59865.44, "Mean Average Height [m]": 30.56, "Electricity [GJ]": 17373.19, "Natural Gas [GJ]": 10982.88, "Water [m3]": 347654.16, "Lat": 41.88485, "Lon": -87.627716, "Weather Location Lat": 41.88485, "Weather Location Lon": -87.627716}, "14697": {"Area [m2]": 192558.26, "Mean Average Height [m]": 49.88, "Electricity [GJ]": 49882.49, "Natural Gas [GJ]": 32170.84, "Water [m3]": 1074406.58, "Lat": 41.884823, "Lon": -87.631134, "Weather Location Lat": 41.884823, "Weather Location Lon": -87.631134}, "14701": {"Area [m2]": 110533.48, "Mean Average Height [m]": 139.41, "Electricity [GJ]": 30199.29, "Natural Gas [GJ]": 23538.72, "Water [m3]": 721448.35, "Lat": 41.8848, "Lon": -87.636841, "Weather Location Lat": 41.8848, "Weather Location Lon": -87.636841}, "14705": {"Area [m2]": 161962.39, "Mean Average Height [m]": 66.31, "Electricity [GJ]": 42694.04, "Natural Gas [GJ]": 30650.17, "Water [m3]": 980363.57, "Lat": 41.884811, "Lon": -87.633423, "Weather Location Lat": 41.884811, "Weather Location Lon": -87.633423}, "14713": {"Area [m2]": 67912.77, "Mean Average Height [m]": 34.36, "Electricity [GJ]": 19350.3, "Natural Gas [GJ]": 12189.02, "Water [m3]": 393378.66, "Lat": 41.884846, "Lon": -87.628845, "Weather Location Lat": 41.884846, "Weather Location Lon": -87.628845}, "14714": {"Area [m2]": 44285.61, "Mean Average Height [m]": 56.4, "Electricity [GJ]": 13924.9, "Natural Gas [GJ]": 11023.4, "Water [m3]": 356105.04, "Lat": 41.884789000000005, "Lon": -87.63797, "Weather Location Lat": 41.884789000000005, "Weather Location Lon": -87.63797}, "14718": {"Area [m2]": 27335.64, "Mean Average Height [m]": 13.32, "Electricity [GJ]": 9188.29, "Natural Gas [GJ]": 1828.91, "Water [m3]": 1526.34, "Lat": 41.8848, "Lon": -87.635681, "Weather Location Lat": 41.8848, "Weather Location Lon": -87.635681}, "14720": {"Area [m2]": 38374.67, "Mean Average Height [m]": 36.54, "Electricity [GJ]": 12154.24, "Natural Gas [GJ]": 7564.27, "Water [m3]": 242926.93, "Lat": 41.8848, "Lon": -87.635681, "Weather Location Lat": 41.8848, "Weather Location Lon": -87.635681}, "14794": {"Area [m2]": 641.13, "Mean Average Height [m]": 10.15, "Electricity [GJ]": 649.12, "Natural Gas [GJ]": 41.8, "Water [m3]": 35.8, "Lat": 41.885689, "Lon": -87.627716, "Weather Location Lat": 41.885689, "Weather Location Lon": -87.627716}, "14933": {"Area [m2]": 6032.8, "Mean Average Height [m]": 11.85, "Electricity [GJ]": 3750.45, "Natural Gas [GJ]": 130.47, "Water [m3]": 336.85, "Lat": 41.885670000000005, "Lon": -87.632263, "Weather Location Lat": 41.885670000000005, "Weather Location Lon": -87.632263}, "14938": {"Area [m2]": 182.54, "Mean Average Height [m]": 11.99, "Electricity [GJ]": 338.17, "Natural Gas [GJ]": 40.36, "Water [m3]": 10.19, "Lat": 41.885661999999996, "Lon": -87.634552, "Weather Location Lat": 41.885661999999996, "Weather Location Lon": -87.634552}, "14944": {"Area [m2]": 677.54, "Mean Average Height [m]": 9.57, "Electricity [GJ]": 614.19, "Natural Gas [GJ]": 43.07, "Water [m3]": 37.83, "Lat": 41.885689, "Lon": -87.627716, "Weather Location Lat": 41.885689, "Weather Location Lon": -87.627716}, "1498": {"Area [m2]": 17981.29, "Mean Average Height [m]": 27.24, "Electricity [GJ]": 7202.24, "Natural Gas [GJ]": 4035.42, "Water [m3]": 129916.31, "Lat": 41.874657, "Lon": -87.628754, "Weather Location Lat": 41.874657, "Weather Location Lon": -87.628754}, "15": {"Area [m2]": 5323.7, "Mean Average Height [m]": 8.31, "Electricity [GJ]": 1996.38, "Natural Gas [GJ]": 323.27, "Water [m3]": 297.26, "Lat": 41.867878000000005, "Lon": -87.625244, "Weather Location Lat": 41.867878000000005, "Weather Location Lon": -87.625244}, "153": {"Area [m2]": 111.81, "Mean Average Height [m]": 8.75, "Electricity [GJ]": 268.67, "Natural Gas [GJ]": 40.29, "Water [m3]": 6.24, "Lat": 41.87294, "Lon": -87.632141, "Weather Location Lat": 41.87294, "Weather Location Lon": -87.632141}, "1534": {"Area [m2]": 38326.57, "Mean Average Height [m]": 42.51, "Electricity [GJ]": 12240.3, "Natural Gas [GJ]": 8116.18, "Water [m3]": 267708.61, "Lat": 41.874649, "Lon": -87.62988299999999, "Weather Location Lat": 41.874649, "Weather Location Lon": -87.62988299999999}, "154": {"Area [m2]": 20725.71, "Mean Average Height [m]": 31.83, "Electricity [GJ]": 7889.76, "Natural Gas [GJ]": 4708.74, "Water [m3]": 150530.41, "Lat": 41.872078, "Lon": -87.633301, "Weather Location Lat": 41.872078, "Weather Location Lon": -87.633301}, "15400": {"Area [m2]": 63638.39, "Mean Average Height [m]": 43.24, "Electricity [GJ]": 18373.82, "Natural Gas [GJ]": 12837.6, "Water [m3]": 384517.6, "Lat": 41.885689, "Lon": -87.627716, "Weather Location Lat": 41.885689, "Weather Location Lon": -87.627716}, "15419": {"Area [m2]": 49787.81, "Mean Average Height [m]": 54.6, "Electricity [GJ]": 14985.45, "Natural Gas [GJ]": 10174.27, "Water [m3]": 311339.21, "Lat": 41.8857, "Lon": -87.626587, "Weather Location Lat": 41.8857, "Weather Location Lon": -87.626587}, "15460": {"Area [m2]": 106185.22, "Mean Average Height [m]": 84.35, "Electricity [GJ]": 28981.86, "Natural Gas [GJ]": 22822.57, "Water [m3]": 655657.27, "Lat": 41.885661999999996, "Lon": -87.633423, "Weather Location Lat": 41.885661999999996, "Weather Location Lon": -87.633423}, "15461": {"Area [m2]": 58732.09, "Mean Average Height [m]": 80.12, "Electricity [GJ]": 17273.76, "Natural Gas [GJ]": 12604.94, "Water [m3]": 384569.4, "Lat": 41.885661999999996, "Lon": -87.634552, "Weather Location Lat": 41.885661999999996, "Weather Location Lon": -87.634552}, "15641": {"Area [m2]": 124719.1, "Mean Average Height [m]": 130.33, "Electricity [GJ]": 33676.9, "Natural Gas [GJ]": 26131.05, "Water [m3]": 801566.83, "Lat": 41.885643, "Lon": -87.636841, "Weather Location Lat": 41.885643, "Weather Location Lon": -87.636841}, "15719": {"Area [m2]": 226660.3, "Mean Average Height [m]": 110.09, "Electricity [GJ]": 58556.92, "Natural Gas [GJ]": 43026.01, "Water [m3]": 1321756.87, "Lat": 41.885719, "Lon": -87.624298, "Weather Location Lat": 41.885719, "Weather Location Lon": -87.624298}, "1574": {"Area [m2]": 28472.35, "Mean Average Height [m]": 49.22, "Electricity [GJ]": 9792.82, "Natural Gas [GJ]": 6556.41, "Water [m3]": 205503.35, "Lat": 41.874638, "Lon": -87.63104200000001, "Weather Location Lat": 41.874638, "Weather Location Lon": -87.63104200000001}, "1580": {"Area [m2]": 25880.84, "Mean Average Height [m]": 36.29, "Electricity [GJ]": 9188.91, "Natural Gas [GJ]": 6134.79, "Water [m3]": 199713.25, "Lat": 41.874649, "Lon": -87.62988299999999, "Weather Location Lat": 41.874649, "Weather Location Lon": -87.62988299999999}, "1586": {"Area [m2]": 18288.3, "Mean Average Height [m]": 26.71, "Electricity [GJ]": 7314.34, "Natural Gas [GJ]": 4436.8, "Water [m3]": 143776.6, "Lat": 41.874657, "Lon": -87.628754, "Weather Location Lat": 41.874657, "Weather Location Lon": -87.628754}, "15879": {"Area [m2]": 35872.55, "Mean Average Height [m]": 69.38, "Electricity [GJ]": 11627.46, "Natural Gas [GJ]": 8349.24, "Water [m3]": 247975.6, "Lat": 41.886532, "Lon": -87.63000500000001, "Weather Location Lat": 41.886532, "Weather Location Lon": -87.63000500000001}, "15886": {"Area [m2]": 56926.14, "Mean Average Height [m]": 42.59, "Electricity [GJ]": 16785.66, "Natural Gas [GJ]": 11007.17, "Water [m3]": 365416.07, "Lat": 41.885708, "Lon": -87.625427, "Weather Location Lat": 41.885708, "Weather Location Lon": -87.625427}, "15897": {"Area [m2]": 49102.53, "Mean Average Height [m]": 55.85, "Electricity [GJ]": 14826.71, "Natural Gas [GJ]": 10201.42, "Water [m3]": 309814.18, "Lat": 41.886547, "Lon": -87.626587, "Weather Location Lat": 41.886547, "Weather Location Lon": -87.626587}, "15943": {"Area [m2]": 148130.04, "Mean Average Height [m]": 95.41, "Electricity [GJ]": 39241.71, "Natural Gas [GJ]": 29564.2, "Water [m3]": 877425.39, "Lat": 41.886542999999996, "Lon": -87.627747, "Weather Location Lat": 41.886542999999996, "Weather Location Lon": -87.627747}, "15948": {"Area [m2]": 112614.98, "Mean Average Height [m]": 80.88, "Electricity [GJ]": 30458.29, "Natural Gas [GJ]": 21774.13, "Water [m3]": 671420.59, "Lat": 41.886517, "Lon": -87.63229399999999, "Weather Location Lat": 41.886517, "Weather Location Lon": -87.63229399999999}, "15966": {"Area [m2]": 565480.81, "Mean Average Height [m]": 84.38, "Electricity [GJ]": 142073.38, "Natural Gas [GJ]": 114768.62, "Water [m3]": 3254409.41, "Lat": 41.885670000000005, "Lon": -87.632263, "Weather Location Lat": 41.885670000000005, "Weather Location Lon": -87.632263}, "15970": {"Area [m2]": 96143.97, "Mean Average Height [m]": 89.34, "Electricity [GJ]": 26689.85, "Natural Gas [GJ]": 19986.93, "Water [m3]": 651826.9, "Lat": 41.885651, "Lon": -87.635712, "Weather Location Lat": 41.885651, "Weather Location Lon": -87.635712}, "15979": {"Area [m2]": 124059.49, "Mean Average Height [m]": 89.27, "Electricity [GJ]": 33305.28, "Natural Gas [GJ]": 24167.95, "Water [m3]": 743859.63, "Lat": 41.886509000000004, "Lon": -87.633423, "Weather Location Lat": 41.886509000000004, "Weather Location Lon": -87.633423}, "15983": {"Area [m2]": 55117.65, "Mean Average Height [m]": 68.83, "Electricity [GJ]": 16350.14, "Natural Gas [GJ]": 11478.14, "Water [m3]": 356230.96, "Lat": 41.886509000000004, "Lon": -87.63458299999999, "Weather Location Lat": 41.886509000000004, "Weather Location Lon": -87.63458299999999}, "1609": {"Area [m2]": 44058.03, "Mean Average Height [m]": 52.82, "Electricity [GJ]": 13670.21, "Natural Gas [GJ]": 9435.1, "Water [m3]": 305426.02, "Lat": 41.874664, "Lon": -87.627625, "Weather Location Lat": 41.874664, "Weather Location Lon": -87.627625}, "1623": {"Area [m2]": 81355.63, "Mean Average Height [m]": 38.41, "Electricity [GJ]": 22685.22, "Natural Gas [GJ]": 14152.63, "Water [m3]": 482438.53, "Lat": 41.874638, "Lon": -87.63104200000001, "Weather Location Lat": 41.874638, "Weather Location Lon": -87.63104200000001}, "16395": {"Area [m2]": 10020.1, "Mean Average Height [m]": 58.1, "Electricity [GJ]": 5245.72, "Natural Gas [GJ]": 3529.54, "Water [m3]": 93193.52, "Lat": 41.886547, "Lon": -87.625458, "Weather Location Lat": 41.886547, "Weather Location Lon": -87.625458}, "16526": {"Area [m2]": 23135.86, "Mean Average Height [m]": 77.78, "Electricity [GJ]": 8547.09, "Natural Gas [GJ]": 6579.77, "Water [m3]": 188565.72, "Lat": 41.88657, "Lon": -87.624298, "Weather Location Lat": 41.88657, "Weather Location Lon": -87.624298}, "16941": {"Area [m2]": 21757.03, "Mean Average Height [m]": 20.63, "Electricity [GJ]": 7798.86, "Natural Gas [GJ]": 1323.13, "Water [m3]": 1214.85, "Lat": 41.886547, "Lon": -87.625458, "Weather Location Lat": 41.886547, "Weather Location Lon": -87.625458}, "16953": {"Area [m2]": 48278.8, "Mean Average Height [m]": 44.16, "Electricity [GJ]": 14685.02, "Natural Gas [GJ]": 10194.15, "Water [m3]": 322812.99, "Lat": 41.886547, "Lon": -87.625458, "Weather Location Lat": 41.886547, "Weather Location Lon": -87.625458}, "1697": {"Area [m2]": 241.89, "Mean Average Height [m]": 13.73, "Electricity [GJ]": 377.34, "Natural Gas [GJ]": 40.47, "Water [m3]": 13.51, "Lat": 41.875465000000005, "Lon": -87.63559000000001, "Weather Location Lat": 41.875465000000005, "Weather Location Lon": -87.63559000000001}, "17": {"Area [m2]": 754.85, "Mean Average Height [m]": 9.03, "Electricity [GJ]": 600.73, "Natural Gas [GJ]": 45.81, "Water [m3]": 42.15, "Lat": 41.867859, "Lon": -87.62982199999999, "Weather Location Lat": 41.867859, "Weather Location Lon": -87.62982199999999}, "1700": {"Area [m2]": 40048.93, "Mean Average Height [m]": 17.49, "Electricity [GJ]": 12644.61, "Natural Gas [GJ]": 2827.15, "Water [m3]": 2236.22, "Lat": 41.874598999999996, "Lon": -87.637878, "Weather Location Lat": 41.874598999999996, "Weather Location Lon": -87.637878}, "1709": {"Area [m2]": 75127.34, "Mean Average Height [m]": 39.88, "Electricity [GJ]": 21231.97, "Natural Gas [GJ]": 13616.92, "Water [m3]": 465591.27, "Lat": 41.874664, "Lon": -87.627625, "Weather Location Lat": 41.874664, "Weather Location Lon": -87.627625}, "17163": {"Area [m2]": 11660.55, "Mean Average Height [m]": 68.68, "Electricity [GJ]": 5645.33, "Natural Gas [GJ]": 3926.49, "Water [m3]": 100076.78, "Lat": 41.887413, "Lon": -87.624329, "Weather Location Lat": 41.887413, "Weather Location Lon": -87.624329}, "173": {"Area [m2]": 8670.61, "Mean Average Height [m]": 12.24, "Electricity [GJ]": 3266.96, "Natural Gas [GJ]": 497.6, "Water [m3]": 484.14, "Lat": 41.872101, "Lon": -87.629852, "Weather Location Lat": 41.872101, "Weather Location Lon": -87.629852}, "1755": {"Area [m2]": 21690.6, "Mean Average Height [m]": 26.26, "Electricity [GJ]": 8059.34, "Natural Gas [GJ]": 4472.73, "Water [m3]": 139887.49, "Lat": 41.875515, "Lon": -87.626465, "Weather Location Lat": 41.875515, "Weather Location Lon": -87.626465}, "1779": {"Area [m2]": 90214.74, "Mean Average Height [m]": 28.02, "Electricity [GJ]": 24884.15, "Natural Gas [GJ]": 17061.92, "Water [m3]": 532041.54, "Lat": 41.874676, "Lon": -87.625336, "Weather Location Lat": 41.874676, "Weather Location Lon": -87.625336}, "18": {"Area [m2]": 754.85, "Mean Average Height [m]": 8.72, "Electricity [GJ]": 588.2, "Natural Gas [GJ]": 46.46, "Water [m3]": 42.15, "Lat": 41.867863, "Lon": -87.628662, "Weather Location Lat": 41.867863, "Weather Location Lon": -87.628662}, "19": {"Area [m2]": 7470.48, "Mean Average Height [m]": 12.03, "Electricity [GJ]": 3634.73, "Natural Gas [GJ]": 246.43, "Water [m3]": 417.13, "Lat": 41.867022999999996, "Lon": -87.62640400000001, "Weather Location Lat": 41.867022999999996, "Weather Location Lon": -87.62640400000001}, "197": {"Area [m2]": 1687.97, "Mean Average Height [m]": 16.87, "Electricity [GJ]": 1095.88, "Natural Gas [GJ]": 59.74, "Water [m3]": 94.25, "Lat": 41.872966999999996, "Lon": -87.62759399999999, "Weather Location Lat": 41.872966999999996, "Weather Location Lon": -87.62759399999999}, "2": {"Area [m2]": 313.14, "Mean Average Height [m]": 2.17, "Electricity [GJ]": 295.28, "Natural Gas [GJ]": 43.49, "Water [m3]": 17.48, "Lat": 41.867859, "Lon": -87.62982199999999, "Weather Location Lat": 41.867859, "Weather Location Lon": -87.62982199999999}, "20": {"Area [m2]": 57765.85, "Mean Average Height [m]": 92.27, "Electricity [GJ]": 17173.97, "Natural Gas [GJ]": 15007.93, "Water [m3]": 408711.93, "Lat": 41.867878000000005, "Lon": -87.625244, "Weather Location Lat": 41.867878000000005, "Weather Location Lon": -87.625244}, "204": {"Area [m2]": 9716.95, "Mean Average Height [m]": 10.54, "Electricity [GJ]": 3521.19, "Natural Gas [GJ]": 594.28, "Water [m3]": 542.57, "Lat": 41.872971, "Lon": -87.626465, "Weather Location Lat": 41.872971, "Weather Location Lon": -87.626465}, "21": {"Area [m2]": 754.83, "Mean Average Height [m]": 9.1, "Electricity [GJ]": 603.45, "Natural Gas [GJ]": 45.66, "Water [m3]": 42.15, "Lat": 41.867859, "Lon": -87.62982199999999, "Weather Location Lat": 41.867859, "Weather Location Lon": -87.62982199999999}, "211": {"Area [m2]": 213532.77, "Mean Average Height [m]": 46.53, "Electricity [GJ]": 61986.23, "Natural Gas [GJ]": 14745.31, "Water [m3]": 11923.05, "Lat": 41.872128000000004, "Lon": -87.62530500000001, "Weather Location Lat": 41.872128000000004, "Weather Location Lon": -87.62530500000001}, "22": {"Area [m2]": 754.84, "Mean Average Height [m]": 8.72, "Electricity [GJ]": 588.2, "Natural Gas [GJ]": 46.46, "Water [m3]": 42.15, "Lat": 41.867863, "Lon": -87.628662, "Weather Location Lat": 41.867863, "Weather Location Lon": -87.628662}, "220": {"Area [m2]": 15853.6, "Mean Average Height [m]": 42.44, "Electricity [GJ]": 6630.95, "Natural Gas [GJ]": 733.44, "Water [m3]": 885.22, "Lat": 41.872952000000005, "Lon": -87.62988299999999, "Weather Location Lat": 41.872952000000005, "Weather Location Lon": -87.62988299999999}, "2248": {"Area [m2]": 668.45, "Mean Average Height [m]": 5.51, "Electricity [GJ]": 499.62, "Natural Gas [GJ]": 46.94, "Water [m3]": 37.32, "Lat": 41.875492, "Lon": -87.62988299999999, "Weather Location Lat": 41.875492, "Weather Location Lon": -87.62988299999999}, "2251": {"Area [m2]": 13851.12, "Mean Average Height [m]": 30.13, "Electricity [GJ]": 6142.33, "Natural Gas [GJ]": 3487.63, "Water [m3]": 97765.98, "Lat": 41.875515, "Lon": -87.626465, "Weather Location Lat": 41.875515, "Weather Location Lon": -87.626465}, "23": {"Area [m2]": 277.11, "Mean Average Height [m]": 7.6, "Electricity [GJ]": 402.4, "Natural Gas [GJ]": 40.41, "Water [m3]": 15.47, "Lat": 41.86787, "Lon": -87.627533, "Weather Location Lat": 41.86787, "Weather Location Lon": -87.627533}, "24": {"Area [m2]": 754.84, "Mean Average Height [m]": 8.73, "Electricity [GJ]": 588.58, "Natural Gas [GJ]": 46.45, "Water [m3]": 42.15, "Lat": 41.867859, "Lon": -87.62982199999999, "Weather Location Lat": 41.867859, "Weather Location Lon": -87.62982199999999}, "25": {"Area [m2]": 754.85, "Mean Average Height [m]": 8.8, "Electricity [GJ]": 591.25, "Natural Gas [GJ]": 46.29, "Water [m3]": 42.15, "Lat": 41.867863, "Lon": -87.628662, "Weather Location Lat": 41.867863, "Weather Location Lon": -87.628662}, "257": {"Area [m2]": 6776.35, "Mean Average Height [m]": 20.9, "Electricity [GJ]": 2994.43, "Natural Gas [GJ]": 305.63, "Water [m3]": 378.37, "Lat": 41.872948, "Lon": -87.631012, "Weather Location Lat": 41.872948, "Weather Location Lon": -87.631012}, "2726": {"Area [m2]": 7364.05, "Mean Average Height [m]": 9.2, "Electricity [GJ]": 2750.46, "Natural Gas [GJ]": 439.47, "Water [m3]": 411.19, "Lat": 41.875481, "Lon": -87.633301, "Weather Location Lat": 41.875481, "Weather Location Lon": -87.633301}, "273": {"Area [m2]": 4714.76, "Mean Average Height [m]": 5.38, "Electricity [GJ]": 1741.6, "Natural Gas [GJ]": 304.57, "Water [m3]": 263.26, "Lat": 41.872971, "Lon": -87.626465, "Weather Location Lat": 41.872971, "Weather Location Lon": -87.626465}, "2861": {"Area [m2]": 14018.56, "Mean Average Height [m]": 16.94, "Electricity [GJ]": 5004.31, "Natural Gas [GJ]": 885.24, "Water [m3]": 782.76, "Lat": 41.876305, "Lon": -87.636749, "Weather Location Lat": 41.876305, "Weather Location Lon": -87.636749}, "2868": {"Area [m2]": 2754.89, "Mean Average Height [m]": 6.75, "Electricity [GJ]": 1330.04, "Natural Gas [GJ]": 128.46, "Water [m3]": 153.83, "Lat": 41.876369, "Lon": -87.62649499999999, "Weather Location Lat": 41.876369, "Weather Location Lon": -87.62649499999999}, "29": {"Area [m2]": 212.72, "Mean Average Height [m]": 3.16, "Electricity [GJ]": 302.91, "Natural Gas [GJ]": 40.6, "Water [m3]": 11.88, "Lat": 41.867859, "Lon": -87.62982199999999, "Weather Location Lat": 41.867859, "Weather Location Lon": -87.62982199999999}, "30": {"Area [m2]": 202.21, "Mean Average Height [m]": 3.2, "Electricity [GJ]": 312.35, "Natural Gas [GJ]": 40.47, "Water [m3]": 11.29, "Lat": 41.867863, "Lon": -87.628662, "Weather Location Lat": 41.867863, "Weather Location Lon": -87.628662}, "305": {"Area [m2]": 23923.18, "Mean Average Height [m]": 28.87, "Electricity [GJ]": 8720.5, "Natural Gas [GJ]": 5800.97, "Water [m3]": 192368.33, "Lat": 41.872955, "Lon": -87.628723, "Weather Location Lat": 41.872955, "Weather Location Lon": -87.628723}, "31": {"Area [m2]": 321.52, "Mean Average Height [m]": 6.94, "Electricity [GJ]": 397.96, "Natural Gas [GJ]": 40.65, "Water [m3]": 17.95, "Lat": 41.86787, "Lon": -87.627533, "Weather Location Lat": 41.86787, "Weather Location Lon": -87.627533}, "32": {"Area [m2]": 11525.83, "Mean Average Height [m]": 15.57, "Electricity [GJ]": 4641.05, "Natural Gas [GJ]": 582.74, "Water [m3]": 643.57, "Lat": 41.867863, "Lon": -87.628662, "Weather Location Lat": 41.867863, "Weather Location Lon": -87.628662}, "3225": {"Area [m2]": 97337.06, "Mean Average Height [m]": 55.49, "Electricity [GJ]": 27372.67, "Natural Gas [GJ]": 23032.94, "Water [m3]": 760393.35, "Lat": 41.874598999999996, "Lon": -87.637878, "Weather Location Lat": 41.874598999999996, "Weather Location Lon": -87.637878}, "323": {"Area [m2]": 3632.11, "Mean Average Height [m]": 9.17, "Electricity [GJ]": 1543.63, "Natural Gas [GJ]": 195.35, "Water [m3]": 202.81, "Lat": 41.873795, "Lon": -87.631012, "Weather Location Lat": 41.873795, "Weather Location Lon": -87.631012}, "3283": {"Area [m2]": 1638.39, "Mean Average Height [m]": 8.17, "Electricity [GJ]": 860.44, "Natural Gas [GJ]": 83.06, "Water [m3]": 91.48, "Lat": 41.876328, "Lon": -87.63333100000001, "Weather Location Lat": 41.876328, "Weather Location Lon": -87.63333100000001}, "3296": {"Area [m2]": 40644.52, "Mean Average Height [m]": 24.53, "Electricity [GJ]": 13954.09, "Natural Gas [GJ]": 2576.64, "Water [m3]": 2269.47, "Lat": 41.875492, "Lon": -87.62988299999999, "Weather Location Lat": 41.875492, "Weather Location Lon": -87.62988299999999}, "329702": {"Area [m2]": 222535.19, "Mean Average Height [m]": 112.41, "Electricity [GJ]": 57734.03, "Natural Gas [GJ]": 41176.18, "Water [m3]": 1368738.92, "Lat": 41.879771999999996, "Lon": -87.625366, "Weather Location Lat": 41.879771999999996, "Weather Location Lon": -87.625366}, "33": {"Area [m2]": 287.75, "Mean Average Height [m]": 3.1, "Electricity [GJ]": 340.73, "Natural Gas [GJ]": 41.05, "Water [m3]": 16.07, "Lat": 41.86871, "Lon": -87.62982199999999, "Weather Location Lat": 41.86871, "Weather Location Lon": -87.62982199999999}, "3346": {"Area [m2]": 96267.38, "Mean Average Height [m]": 141.68, "Electricity [GJ]": 26649.74, "Natural Gas [GJ]": 22378.91, "Water [m3]": 626458.39, "Lat": 41.87632, "Lon": -87.63446, "Weather Location Lat": 41.87632, "Weather Location Lon": -87.63446}, "3353": {"Area [m2]": 11330.45, "Mean Average Height [m]": 28.73, "Electricity [GJ]": 5530.27, "Natural Gas [GJ]": 2922.14, "Water [m3]": 87399.75, "Lat": 41.87632, "Lon": -87.63446, "Weather Location Lat": 41.87632, "Weather Location Lon": -87.63446}, "3363": {"Area [m2]": 9498.55, "Mean Average Height [m]": 17.47, "Electricity [GJ]": 3706.41, "Natural Gas [GJ]": 529.99, "Water [m3]": 530.37, "Lat": 41.876328, "Lon": -87.63333100000001, "Weather Location Lat": 41.876328, "Weather Location Lon": -87.63333100000001}, "3372": {"Area [m2]": 48280.9, "Mean Average Height [m]": 39.43, "Electricity [GJ]": 14711.37, "Natural Gas [GJ]": 9809.86, "Water [m3]": 331954.16, "Lat": 41.875484, "Lon": -87.632172, "Weather Location Lat": 41.875484, "Weather Location Lon": -87.632172}, "3375": {"Area [m2]": 12591.04, "Mean Average Height [m]": 11.93, "Electricity [GJ]": 4530.87, "Natural Gas [GJ]": 761.92, "Water [m3]": 703.05, "Lat": 41.876339, "Lon": -87.63104200000001, "Weather Location Lat": 41.876339, "Weather Location Lon": -87.63104200000001}, "34": {"Area [m2]": 287.76, "Mean Average Height [m]": 2.99, "Electricity [GJ]": 334.14, "Natural Gas [GJ]": 41.15, "Water [m3]": 16.07, "Lat": 41.86871, "Lon": -87.628693, "Weather Location Lat": 41.86871, "Weather Location Lon": -87.628693}, "3416": {"Area [m2]": 43130.38, "Mean Average Height [m]": 54.5, "Electricity [GJ]": 13583.47, "Natural Gas [GJ]": 10301.16, "Water [m3]": 335986.28, "Lat": 41.875496000000005, "Lon": -87.628754, "Weather Location Lat": 41.875496000000005, "Weather Location Lon": -87.628754}, "3421": {"Area [m2]": 121960.34, "Mean Average Height [m]": 47.61, "Electricity [GJ]": 32669.8, "Natural Gas [GJ]": 20564.43, "Water [m3]": 715937.22, "Lat": 41.875496000000005, "Lon": -87.628754, "Weather Location Lat": 41.875496000000005, "Weather Location Lon": -87.628754}, "3476": {"Area [m2]": 75573.74, "Mean Average Height [m]": 38.81, "Electricity [GJ]": 21351.15, "Natural Gas [GJ]": 13661.65, "Water [m3]": 471445.22, "Lat": 41.875507, "Lon": -87.627625, "Weather Location Lat": 41.875507, "Weather Location Lon": -87.627625}, "35": {"Area [m2]": 777.71, "Mean Average Height [m]": 9.01, "Electricity [GJ]": 612.19, "Natural Gas [GJ]": 46.2, "Water [m3]": 43.43, "Lat": 41.86871, "Lon": -87.62982199999999, "Weather Location Lat": 41.86871, "Weather Location Lon": -87.62982199999999}, "3518": {"Area [m2]": 184934.75, "Mean Average Height [m]": 47.46, "Electricity [GJ]": 48064.5, "Natural Gas [GJ]": 31439.04, "Water [m3]": 1047321.88, "Lat": 41.875526, "Lon": -87.625336, "Weather Location Lat": 41.875526, "Weather Location Lon": -87.625336}, "3553": {"Area [m2]": 312.69, "Mean Average Height [m]": 9.89, "Electricity [GJ]": 603.34, "Natural Gas [GJ]": 40.38, "Water [m3]": 17.46, "Lat": 41.877209, "Lon": -87.62649499999999, "Weather Location Lat": 41.877209, "Weather Location Lon": -87.62649499999999}, "36": {"Area [m2]": 777.71, "Mean Average Height [m]": 8.42, "Electricity [GJ]": 588.23, "Natural Gas [GJ]": 47.67, "Water [m3]": 43.43, "Lat": 41.86871, "Lon": -87.628693, "Weather Location Lat": 41.86871, "Weather Location Lon": -87.628693}, "3684": {"Area [m2]": 1246.94, "Mean Average Height [m]": 9.43, "Electricity [GJ]": 1038.93, "Natural Gas [GJ]": 44.59, "Water [m3]": 69.63, "Lat": 41.877186, "Lon": -87.632202, "Weather Location Lat": 41.877186, "Weather Location Lon": -87.632202}, "37": {"Area [m2]": 12836.72, "Mean Average Height [m]": 22.36, "Electricity [GJ]": 4826.63, "Natural Gas [GJ]": 734.65, "Water [m3]": 716.77, "Lat": 41.86787, "Lon": -87.62640400000001, "Weather Location Lat": 41.86787, "Weather Location Lon": -87.62640400000001}, "3713": {"Area [m2]": 6121.09, "Mean Average Height [m]": 10.69, "Electricity [GJ]": 2957.76, "Natural Gas [GJ]": 243.4, "Water [m3]": 341.78, "Lat": 41.877193, "Lon": -87.628784, "Weather Location Lat": 41.877193, "Weather Location Lon": -87.628784}, "3718": {"Area [m2]": 411.92, "Mean Average Height [m]": 8.36, "Electricity [GJ]": 505.2, "Natural Gas [GJ]": 40.82, "Water [m3]": 23.0, "Lat": 41.877209, "Lon": -87.62649499999999, "Weather Location Lat": 41.877209, "Weather Location Lon": -87.62649499999999}, "38": {"Area [m2]": 426.33, "Mean Average Height [m]": 8.9, "Electricity [GJ]": 485.86, "Natural Gas [GJ]": 41.07, "Water [m3]": 23.81, "Lat": 41.86871, "Lon": -87.62982199999999, "Weather Location Lat": 41.86871, "Weather Location Lon": -87.62982199999999}, "39": {"Area [m2]": 426.34, "Mean Average Height [m]": 8.79, "Electricity [GJ]": 481.88, "Natural Gas [GJ]": 41.1, "Water [m3]": 23.81, "Lat": 41.86871, "Lon": -87.628693, "Weather Location Lat": 41.86871, "Weather Location Lon": -87.628693}, "3932": {"Area [m2]": 19327.27, "Mean Average Height [m]": 46.8, "Electricity [GJ]": 7550.53, "Natural Gas [GJ]": 5369.05, "Water [m3]": 140885.64, "Lat": 41.877167, "Lon": -87.63446, "Weather Location Lat": 41.877167, "Weather Location Lon": -87.63446}, "4": {"Area [m2]": 251.16, "Mean Average Height [m]": 2.97, "Electricity [GJ]": 303.2, "Natural Gas [GJ]": 41.07, "Water [m3]": 14.02, "Lat": 41.867859, "Lon": -87.62982199999999, "Weather Location Lat": 41.867859, "Weather Location Lon": -87.62982199999999}, "41": {"Area [m2]": 11190.57, "Mean Average Height [m]": 33.28, "Electricity [GJ]": 5505.99, "Natural Gas [GJ]": 2955.24, "Water [m3]": 88848.63, "Lat": 41.868675, "Lon": -87.635529, "Weather Location Lat": 41.868675, "Weather Location Lon": -87.635529}, "419": {"Area [m2]": 59710.8, "Mean Average Height [m]": 31.19, "Electricity [GJ]": 17567.75, "Natural Gas [GJ]": 11747.37, "Water [m3]": 410169.97, "Lat": 41.872105, "Lon": -87.628723, "Weather Location Lat": 41.872105, "Weather Location Lon": -87.628723}, "45": {"Area [m2]": 309.11, "Mean Average Height [m]": 6.86, "Electricity [GJ]": 385.88, "Natural Gas [GJ]": 40.64, "Water [m3]": 17.26, "Lat": 41.868717, "Lon": -87.627563, "Weather Location Lat": 41.868717, "Weather Location Lon": -87.627563}, "46": {"Area [m2]": 51734.1, "Mean Average Height [m]": 12.51, "Electricity [GJ]": 15516.08, "Natural Gas [GJ]": 3702.54, "Water [m3]": 2888.68, "Lat": 41.867851, "Lon": -87.630951, "Weather Location Lat": 41.867851, "Weather Location Lon": -87.630951}, "48": {"Area [m2]": 269.96, "Mean Average Height [m]": 7.48, "Electricity [GJ]": 394.47, "Natural Gas [GJ]": 40.41, "Water [m3]": 15.07, "Lat": 41.868717, "Lon": -87.627563, "Weather Location Lat": 41.868717, "Weather Location Lon": -87.627563}, "49": {"Area [m2]": 11572.7, "Mean Average Height [m]": 15.46, "Electricity [GJ]": 4633.73, "Natural Gas [GJ]": 592.42, "Water [m3]": 646.19, "Lat": 41.86871, "Lon": -87.628693, "Weather Location Lat": 41.86871, "Weather Location Lon": -87.628693}, "4958": {"Area [m2]": 186219.86, "Mean Average Height [m]": 129.83, "Electricity [GJ]": 48912.15, "Natural Gas [GJ]": 40518.3, "Water [m3]": 1162395.22, "Lat": 41.877151, "Lon": -87.636749, "Weather Location Lat": 41.877151, "Weather Location Lon": -87.636749}, "5": {"Area [m2]": 288.21, "Mean Average Height [m]": 3.03, "Electricity [GJ]": 330.35, "Natural Gas [GJ]": 41.22, "Water [m3]": 16.09, "Lat": 41.867863, "Lon": -87.628662, "Weather Location Lat": 41.867863, "Weather Location Lon": -87.628662}, "50": {"Area [m2]": 223.63, "Mean Average Height [m]": 3.68, "Electricity [GJ]": 326.01, "Natural Gas [GJ]": 40.44, "Water [m3]": 12.49, "Lat": 41.868671, "Lon": -87.636658, "Weather Location Lat": 41.868671, "Weather Location Lon": -87.636658}, "5099": {"Area [m2]": 88732.3, "Mean Average Height [m]": 52.68, "Electricity [GJ]": 24654.49, "Natural Gas [GJ]": 16486.03, "Water [m3]": 563178.59, "Lat": 41.877205, "Lon": -87.627625, "Weather Location Lat": 41.877205, "Weather Location Lon": -87.627625}, "51": {"Area [m2]": 4257.49, "Mean Average Height [m]": 5.42, "Electricity [GJ]": 2088.66, "Natural Gas [GJ]": 166.36, "Water [m3]": 237.73, "Lat": 41.86871, "Lon": -87.62982199999999, "Weather Location Lat": 41.86871, "Weather Location Lon": -87.62982199999999}, "5100": {"Area [m2]": 56739.87, "Mean Average Height [m]": 108.53, "Electricity [GJ]": 17063.91, "Natural Gas [GJ]": 14469.34, "Water [m3]": 443654.24, "Lat": 41.877151, "Lon": -87.636749, "Weather Location Lat": 41.877151, "Weather Location Lon": -87.636749}, "5108": {"Area [m2]": 23463.31, "Mean Average Height [m]": 49.34, "Electricity [GJ]": 8564.06, "Natural Gas [GJ]": 5717.44, "Water [m3]": 163201.12, "Lat": 41.878009999999996, "Lon": -87.634491, "Weather Location Lat": 41.878009999999996, "Weather Location Lon": -87.634491}, "5113": {"Area [m2]": 87173.04, "Mean Average Height [m]": 33.97, "Electricity [GJ]": 24230.88, "Natural Gas [GJ]": 17449.46, "Water [m3]": 538205.67, "Lat": 41.877167, "Lon": -87.63446, "Weather Location Lat": 41.877167, "Weather Location Lon": -87.63446}, "5114": {"Area [m2]": 226759.69, "Mean Average Height [m]": 84.11, "Electricity [GJ]": 58482.04, "Natural Gas [GJ]": 38376.07, "Water [m3]": 1324555.98, "Lat": 41.877178, "Lon": -87.63333100000001, "Weather Location Lat": 41.877178, "Weather Location Lon": -87.63333100000001}, "5133": {"Area [m2]": 538351.89, "Mean Average Height [m]": 46.17, "Electricity [GJ]": 137147.96, "Natural Gas [GJ]": 133218.11, "Water [m3]": 3498046.3, "Lat": 41.87294, "Lon": -87.632141, "Weather Location Lat": 41.87294, "Weather Location Lon": -87.632141}, "5152": {"Area [m2]": 90138.58, "Mean Average Height [m]": 72.49, "Electricity [GJ]": 25212.22, "Natural Gas [GJ]": 18729.67, "Water [m3]": 620961.08, "Lat": 41.877186, "Lon": -87.63104200000001, "Weather Location Lat": 41.877186, "Weather Location Lon": -87.63104200000001}, "5153": {"Area [m2]": 54238.02, "Mean Average Height [m]": 59.84, "Electricity [GJ]": 16452.87, "Natural Gas [GJ]": 13607.59, "Water [m3]": 432984.26, "Lat": 41.87719, "Lon": -87.629913, "Weather Location Lat": 41.87719, "Weather Location Lon": -87.629913}, "5160": {"Area [m2]": 64306.58, "Mean Average Height [m]": 50.42, "Electricity [GJ]": 18731.22, "Natural Gas [GJ]": 13109.06, "Water [m3]": 443214.35, "Lat": 41.87719, "Lon": -87.629913, "Weather Location Lat": 41.87719, "Weather Location Lon": -87.629913}, "5172": {"Area [m2]": 68877.34, "Mean Average Height [m]": 83.6, "Electricity [GJ]": 19804.87, "Natural Gas [GJ]": 15653.15, "Water [m3]": 448127.89, "Lat": 41.878029, "Lon": -87.632202, "Weather Location Lat": 41.878029, "Weather Location Lon": -87.632202}, "5178": {"Area [m2]": 46214.38, "Mean Average Height [m]": 33.98, "Electricity [GJ]": 14177.45, "Natural Gas [GJ]": 10397.27, "Water [m3]": 310808.48, "Lat": 41.877193, "Lon": -87.628784, "Weather Location Lat": 41.877193, "Weather Location Lon": -87.628784}, "5187": {"Area [m2]": 49671.04, "Mean Average Height [m]": 54.32, "Electricity [GJ]": 15228.01, "Natural Gas [GJ]": 11589.63, "Water [m3]": 383228.35, "Lat": 41.877193, "Lon": -87.628784, "Weather Location Lat": 41.877193, "Weather Location Lon": -87.628784}, "52": {"Area [m2]": 65038.67, "Mean Average Height [m]": 25.01, "Electricity [GJ]": 18783.02, "Natural Gas [GJ]": 11597.79, "Water [m3]": 417969.25, "Lat": 41.86787, "Lon": -87.627533, "Weather Location Lat": 41.86787, "Weather Location Lon": -87.627533}, "5277": {"Area [m2]": 40999.55, "Mean Average Height [m]": 60.48, "Electricity [GJ]": 12851.23, "Natural Gas [GJ]": 8986.05, "Water [m3]": 270390.62, "Lat": 41.878067, "Lon": -87.62649499999999, "Weather Location Lat": 41.878067, "Weather Location Lon": -87.62649499999999}, "53": {"Area [m2]": 4424.07, "Mean Average Height [m]": 5.39, "Electricity [GJ]": 2139.19, "Natural Gas [GJ]": 177.56, "Water [m3]": 247.03, "Lat": 41.86871, "Lon": -87.62982199999999, "Weather Location Lat": 41.86871, "Weather Location Lon": -87.62982199999999}, "5347": {"Area [m2]": 398666.41, "Mean Average Height [m]": 94.92, "Electricity [GJ]": 100716.17, "Natural Gas [GJ]": 72631.96, "Water [m3]": 2278870.92, "Lat": 41.877224, "Lon": -87.625366, "Weather Location Lat": 41.877224, "Weather Location Lon": -87.625366}, "55": {"Area [m2]": 35773.8, "Mean Average Height [m]": 31.43, "Electricity [GJ]": 11515.77, "Natural Gas [GJ]": 6896.51, "Water [m3]": 230215.57, "Lat": 41.868725, "Lon": -87.62640400000001, "Weather Location Lat": 41.868725, "Weather Location Lon": -87.62640400000001}, "56": {"Area [m2]": 150984.79, "Mean Average Height [m]": 36.98, "Electricity [GJ]": 39872.46, "Natural Gas [GJ]": 27661.33, "Water [m3]": 890478.71, "Lat": 41.867878000000005, "Lon": -87.625244, "Weather Location Lat": 41.867878000000005, "Weather Location Lon": -87.625244}, "57": {"Area [m2]": 164.32, "Mean Average Height [m]": 4.88, "Electricity [GJ]": 245.9, "Natural Gas [GJ]": 40.57, "Water [m3]": 9.18, "Lat": 41.869514, "Lon": -87.636688, "Weather Location Lat": 41.869514, "Weather Location Lon": -87.636688}, "5845": {"Area [m2]": 2680.74, "Mean Average Height [m]": 10.05, "Electricity [GJ]": 1291.33, "Natural Gas [GJ]": 126.29, "Water [m3]": 149.68, "Lat": 41.878006, "Lon": -87.63561999999999, "Weather Location Lat": 41.878006, "Weather Location Lon": -87.63561999999999}, "59": {"Area [m2]": 261.21, "Mean Average Height [m]": 3.34, "Electricity [GJ]": 303.33, "Natural Gas [GJ]": 41.15, "Water [m3]": 14.59, "Lat": 41.86953, "Lon": -87.63324, "Weather Location Lat": 41.86953, "Weather Location Lon": -87.63324}, "5914": {"Area [m2]": 134.91, "Mean Average Height [m]": 2.28, "Electricity [GJ]": 203.98, "Natural Gas [GJ]": 40.84, "Water [m3]": 7.53, "Lat": 41.878853, "Lon": -87.63678, "Weather Location Lat": 41.878853, "Weather Location Lon": -87.63678}, "599": {"Area [m2]": 9866.64, "Mean Average Height [m]": 13.28, "Electricity [GJ]": 3909.76, "Natural Gas [GJ]": 526.65, "Water [m3]": 550.92, "Lat": 41.873814, "Lon": -87.626465, "Weather Location Lat": 41.873814, "Weather Location Lon": -87.626465}, "603": {"Area [m2]": 177629.75, "Mean Average Height [m]": 43.17, "Electricity [GJ]": 46284.93, "Natural Gas [GJ]": 31190.12, "Water [m3]": 1006383.54, "Lat": 41.872982, "Lon": -87.62530500000001, "Weather Location Lat": 41.872982, "Weather Location Lon": -87.62530500000001}, "6077": {"Area [m2]": 119099.21, "Mean Average Height [m]": 141.54, "Electricity [GJ]": 32259.61, "Natural Gas [GJ]": 25899.21, "Water [m3]": 755573.25, "Lat": 41.878044, "Lon": -87.629913, "Weather Location Lat": 41.878044, "Weather Location Lon": -87.629913}, "61": {"Area [m2]": 3319.28, "Mean Average Height [m]": 11.49, "Electricity [GJ]": 1524.64, "Natural Gas [GJ]": 156.9, "Water [m3]": 185.34, "Lat": 41.868671, "Lon": -87.636658, "Weather Location Lat": 41.868671, "Weather Location Lon": -87.636658}, "620": {"Area [m2]": 414615.57, "Mean Average Height [m]": 24.34, "Electricity [GJ]": 103689.22, "Natural Gas [GJ]": 62617.72, "Water [m3]": 2128194.55, "Lat": 41.872046999999995, "Lon": -87.638977, "Weather Location Lat": 41.872046999999995, "Weather Location Lon": -87.638977}, "6213": {"Area [m2]": 33456.85, "Mean Average Height [m]": 53.63, "Electricity [GJ]": 11026.66, "Natural Gas [GJ]": 7740.99, "Water [m3]": 234647.1, "Lat": 41.877995, "Lon": -87.637909, "Weather Location Lat": 41.877995, "Weather Location Lon": -87.637909}, "6229": {"Area [m2]": 109508.18, "Mean Average Height [m]": 63.09, "Electricity [GJ]": 29632.88, "Natural Gas [GJ]": 20143.04, "Water [m3]": 645600.31, "Lat": 41.878009999999996, "Lon": -87.634491, "Weather Location Lat": 41.878009999999996, "Weather Location Lon": -87.634491}, "6281": {"Area [m2]": 20591.53, "Mean Average Height [m]": 21.89, "Electricity [GJ]": 7128.7, "Natural Gas [GJ]": 1317.14, "Water [m3]": 1149.77, "Lat": 41.878052000000004, "Lon": -87.628784, "Weather Location Lat": 41.878052000000004, "Weather Location Lon": -87.628784}, "6291": {"Area [m2]": 140929.95, "Mean Average Height [m]": 80.27, "Electricity [GJ]": 37385.98, "Natural Gas [GJ]": 25842.96, "Water [m3]": 829079.68, "Lat": 41.878029, "Lon": -87.632202, "Weather Location Lat": 41.878029, "Weather Location Lon": -87.632202}, "6343": {"Area [m2]": 120810.32, "Mean Average Height [m]": 70.98, "Electricity [GJ]": 32455.17, "Natural Gas [GJ]": 22723.26, "Water [m3]": 718467.05, "Lat": 41.878021000000004, "Lon": -87.633362, "Weather Location Lat": 41.878021000000004, "Weather Location Lon": -87.633362}, "64": {"Area [m2]": 163.43, "Mean Average Height [m]": 3.66, "Electricity [GJ]": 265.75, "Natural Gas [GJ]": 40.45, "Water [m3]": 9.13, "Lat": 41.869514, "Lon": -87.636688, "Weather Location Lat": 41.869514, "Weather Location Lon": -87.636688}, "643": {"Area [m2]": 181.54, "Mean Average Height [m]": 13.18, "Electricity [GJ]": 360.92, "Natural Gas [GJ]": 40.31, "Water [m3]": 10.14, "Lat": 41.874607, "Lon": -87.636719, "Weather Location Lat": 41.874607, "Weather Location Lon": -87.636719}, "655": {"Area [m2]": 119167.37, "Mean Average Height [m]": 53.52, "Electricity [GJ]": 32419.16, "Natural Gas [GJ]": 23308.77, "Water [m3]": 806479.91, "Lat": 41.872925, "Lon": -87.633301, "Weather Location Lat": 41.872925, "Weather Location Lon": -87.633301}, "656": {"Area [m2]": 19623.22, "Mean Average Height [m]": 35.78, "Electricity [GJ]": 7602.64, "Natural Gas [GJ]": 4519.49, "Water [m3]": 140635.83, "Lat": 41.873775, "Lon": -87.633301, "Weather Location Lat": 41.873775, "Weather Location Lon": -87.633301}, "657": {"Area [m2]": 1561.25, "Mean Average Height [m]": 5.35, "Electricity [GJ]": 808.31, "Natural Gas [GJ]": 84.56, "Water [m3]": 87.18, "Lat": 41.873795, "Lon": -87.631012, "Weather Location Lat": 41.873795, "Weather Location Lon": -87.631012}, "661": {"Area [m2]": 23262.74, "Mean Average Height [m]": 28.21, "Electricity [GJ]": 8514.32, "Natural Gas [GJ]": 5026.35, "Water [m3]": 164303.69, "Lat": 41.873795, "Lon": -87.631012, "Weather Location Lat": 41.873795, "Weather Location Lon": -87.631012}, "665": {"Area [m2]": 100071.74, "Mean Average Height [m]": 38.79, "Electricity [GJ]": 27652.57, "Natural Gas [GJ]": 19434.84, "Water [m3]": 682776.86, "Lat": 41.872093, "Lon": -87.631012, "Weather Location Lat": 41.872093, "Weather Location Lon": -87.631012}, "668": {"Area [m2]": 71988.57, "Mean Average Height [m]": 30.01, "Electricity [GJ]": 20650.87, "Natural Gas [GJ]": 14411.71, "Water [m3]": 496534.48, "Lat": 41.872101, "Lon": -87.629852, "Weather Location Lat": 41.872101, "Weather Location Lon": -87.629852}, "671": {"Area [m2]": 46857.05, "Mean Average Height [m]": 74.59, "Electricity [GJ]": 14580.39, "Natural Gas [GJ]": 11854.28, "Water [m3]": 375539.44, "Lat": 41.873798, "Lon": -87.62988299999999, "Weather Location Lat": 41.873798, "Weather Location Lon": -87.62988299999999}, "675": {"Area [m2]": 19644.48, "Mean Average Height [m]": 15.67, "Electricity [GJ]": 7799.9, "Natural Gas [GJ]": 1014.7, "Water [m3]": 1096.89, "Lat": 41.873798, "Lon": -87.628723, "Weather Location Lat": 41.873798, "Weather Location Lon": -87.628723}, "68": {"Area [m2]": 6803.81, "Mean Average Height [m]": 12.7, "Electricity [GJ]": 2715.94, "Natural Gas [GJ]": 369.34, "Water [m3]": 379.91, "Lat": 41.869568, "Lon": -87.627563, "Weather Location Lat": 41.869568, "Weather Location Lon": -87.627563}, "6823": {"Area [m2]": 1744.27, "Mean Average Height [m]": 11.45, "Electricity [GJ]": 1369.26, "Natural Gas [GJ]": 45.05, "Water [m3]": 97.4, "Lat": 41.878871999999994, "Lon": -87.633362, "Weather Location Lat": 41.878871999999994, "Weather Location Lon": -87.633362}, "6854": {"Area [m2]": 1370.27, "Mean Average Height [m]": 10.53, "Electricity [GJ]": 1304.96, "Natural Gas [GJ]": 41.61, "Water [m3]": 76.51, "Lat": 41.878871999999994, "Lon": -87.633362, "Weather Location Lat": 41.878871999999994, "Weather Location Lon": -87.633362}, "6855": {"Area [m2]": 579.31, "Mean Average Height [m]": 15.02, "Electricity [GJ]": 613.27, "Natural Gas [GJ]": 41.49, "Water [m3]": 32.35, "Lat": 41.878899, "Lon": -87.628784, "Weather Location Lat": 41.878899, "Weather Location Lon": -87.628784}, "70": {"Area [m2]": 85153.09, "Mean Average Height [m]": 19.58, "Electricity [GJ]": 25945.07, "Natural Gas [GJ]": 5952.32, "Water [m3]": 4754.7, "Lat": 41.867798, "Lon": -87.638947, "Weather Location Lat": 41.867798, "Weather Location Lon": -87.638947}, "7043": {"Area [m2]": 344360.91, "Mean Average Height [m]": 166.18, "Electricity [GJ]": 87481.01, "Natural Gas [GJ]": 64208.56, "Water [m3]": 1995180.84, "Lat": 41.878853, "Lon": -87.63678, "Weather Location Lat": 41.878853, "Weather Location Lon": -87.63678}, "71": {"Area [m2]": 10589.69, "Mean Average Height [m]": 23.84, "Electricity [GJ]": 5333.73, "Natural Gas [GJ]": 2621.66, "Water [m3]": 80893.57, "Lat": 41.869578999999995, "Lon": -87.625275, "Weather Location Lat": 41.869578999999995, "Weather Location Lon": -87.625275}, "7192": {"Area [m2]": 86599.51, "Mean Average Height [m]": 116.57, "Electricity [GJ]": 24242.25, "Natural Gas [GJ]": 18783.44, "Water [m3]": 571220.92, "Lat": 41.878845, "Lon": -87.637909, "Weather Location Lat": 41.878845, "Weather Location Lon": -87.637909}, "7196": {"Area [m2]": 28315.08, "Mean Average Height [m]": 11.51, "Electricity [GJ]": 8789.94, "Natural Gas [GJ]": 2056.32, "Water [m3]": 1581.03, "Lat": 41.878857, "Lon": -87.63561999999999, "Weather Location Lat": 41.878857, "Weather Location Lon": -87.63561999999999}, "72": {"Area [m2]": 370.72, "Mean Average Height [m]": 7.37, "Electricity [GJ]": 433.96, "Natural Gas [GJ]": 40.8, "Water [m3]": 20.7, "Lat": 41.869568, "Lon": -87.627563, "Weather Location Lat": 41.869568, "Weather Location Lon": -87.627563}, "7200": {"Area [m2]": 138949.92, "Mean Average Height [m]": 94.73, "Electricity [GJ]": 37245.75, "Natural Gas [GJ]": 27487.6, "Water [m3]": 906385.48, "Lat": 41.878052000000004, "Lon": -87.628784, "Weather Location Lat": 41.878052000000004, "Weather Location Lon": -87.628784}, "7236": {"Area [m2]": 60296.52, "Mean Average Height [m]": 88.59, "Electricity [GJ]": 17713.06, "Natural Gas [GJ]": 13230.72, "Water [m3]": 409181.18, "Lat": 41.878895, "Lon": -87.631073, "Weather Location Lat": 41.878895, "Weather Location Lon": -87.631073}, "7239": {"Area [m2]": 45468.04, "Mean Average Height [m]": 46.56, "Electricity [GJ]": 13925.85, "Natural Gas [GJ]": 9132.87, "Water [m3]": 290867.71, "Lat": 41.878883, "Lon": -87.632202, "Weather Location Lat": 41.878883, "Weather Location Lon": -87.632202}, "7240": {"Area [m2]": 14235.17, "Mean Average Height [m]": 9.46, "Electricity [GJ]": 4733.77, "Natural Gas [GJ]": 967.4, "Water [m3]": 794.85, "Lat": 41.878895, "Lon": -87.631073, "Weather Location Lat": 41.878895, "Weather Location Lon": -87.631073}, "7254": {"Area [m2]": 39508.94, "Mean Average Height [m]": 44.02, "Electricity [GJ]": 12503.16, "Natural Gas [GJ]": 9496.0, "Water [m3]": 263220.3, "Lat": 41.878899, "Lon": -87.628784, "Weather Location Lat": 41.878899, "Weather Location Lon": -87.628784}, "7297": {"Area [m2]": 82099.27, "Mean Average Height [m]": 44.64, "Electricity [GJ]": 23013.01, "Natural Gas [GJ]": 15485.86, "Water [m3]": 522477.74, "Lat": 41.878056, "Lon": -87.627625, "Weather Location Lat": 41.878056, "Weather Location Lon": -87.627625}, "7319": {"Area [m2]": 83361.25, "Mean Average Height [m]": 39.37, "Electricity [GJ]": 23317.08, "Natural Gas [GJ]": 16723.05, "Water [m3]": 524153.2, "Lat": 41.878067, "Lon": -87.62649499999999, "Weather Location Lat": 41.878067, "Weather Location Lon": -87.62649499999999}, "7336": {"Area [m2]": 171187.34, "Mean Average Height [m]": 49.8, "Electricity [GJ]": 44880.81, "Natural Gas [GJ]": 33172.81, "Water [m3]": 1009577.89, "Lat": 41.878067, "Lon": -87.625366, "Weather Location Lat": 41.878067, "Weather Location Lon": -87.625366}, "74": {"Area [m2]": 14361.41, "Mean Average Height [m]": 24.99, "Electricity [GJ]": 6272.16, "Natural Gas [GJ]": 3262.64, "Water [m3]": 102612.35, "Lat": 41.869578999999995, "Lon": -87.625275, "Weather Location Lat": 41.869578999999995, "Weather Location Lon": -87.625275}, "75": {"Area [m2]": 4766.52, "Mean Average Height [m]": 5.34, "Electricity [GJ]": 2283.74, "Natural Gas [GJ]": 192.69, "Water [m3]": 266.15, "Lat": 41.86956, "Lon": -87.62982199999999, "Weather Location Lat": 41.86956, "Weather Location Lon": -87.62982199999999}, "76": {"Area [m2]": 4209.18, "Mean Average Height [m]": 5.21, "Electricity [GJ]": 2015.99, "Natural Gas [GJ]": 171.83, "Water [m3]": 235.03, "Lat": 41.86956, "Lon": -87.62982199999999, "Weather Location Lat": 41.86956, "Weather Location Lon": -87.62982199999999}, "77": {"Area [m2]": 386.18, "Mean Average Height [m]": 7.44, "Electricity [GJ]": 442.89, "Natural Gas [GJ]": 40.86, "Water [m3]": 21.56, "Lat": 41.869568, "Lon": -87.627563, "Weather Location Lat": 41.869568, "Weather Location Lon": -87.627563}, "78": {"Area [m2]": 11964.42, "Mean Average Height [m]": 15.6, "Electricity [GJ]": 4764.53, "Natural Gas [GJ]": 618.85, "Water [m3]": 668.06, "Lat": 41.869564000000004, "Lon": -87.628693, "Weather Location Lat": 41.869564000000004, "Weather Location Lon": -87.628693}, "79": {"Area [m2]": 148735.55, "Mean Average Height [m]": 22.16, "Electricity [GJ]": 47843.54, "Natural Gas [GJ]": 8988.19, "Water [m3]": 8304.96, "Lat": 41.867832, "Lon": -87.63324, "Weather Location Lat": 41.867832, "Weather Location Lon": -87.63324}, "8063": {"Area [m2]": 52113.85, "Mean Average Height [m]": 94.58, "Electricity [GJ]": 15690.42, "Natural Gas [GJ]": 12065.0, "Water [m3]": 358657.28, "Lat": 41.879684000000005, "Lon": -87.637939, "Weather Location Lat": 41.879684000000005, "Weather Location Lon": -87.637939}, "8117": {"Area [m2]": 24590.49, "Mean Average Height [m]": 38.85, "Electricity [GJ]": 8817.21, "Natural Gas [GJ]": 5585.34, "Water [m3]": 164475.23, "Lat": 41.879761, "Lon": -87.626526, "Weather Location Lat": 41.879761, "Weather Location Lon": -87.626526}, "82": {"Area [m2]": 13307.54, "Mean Average Height [m]": 52.07, "Electricity [GJ]": 6025.74, "Natural Gas [GJ]": 3918.06, "Water [m3]": 103506.8, "Lat": 41.870407, "Lon": -87.628723, "Weather Location Lat": 41.870407, "Weather Location Lon": -87.628723}, "8330": {"Area [m2]": 54489.63, "Mean Average Height [m]": 49.71, "Electricity [GJ]": 16149.75, "Natural Gas [GJ]": 10865.43, "Water [m3]": 343379.12, "Lat": 41.879704, "Lon": -87.635651, "Weather Location Lat": 41.879704, "Weather Location Lon": -87.635651}, "8340": {"Area [m2]": 2521.97, "Mean Average Height [m]": 10.44, "Electricity [GJ]": 2207.48, "Natural Gas [GJ]": 44.67, "Water [m3]": 140.82, "Lat": 41.878914, "Lon": -87.626526, "Weather Location Lat": 41.878914, "Weather Location Lon": -87.626526}, "8398": {"Area [m2]": 38841.21, "Mean Average Height [m]": 34.21, "Electricity [GJ]": 12264.66, "Natural Gas [GJ]": 7586.01, "Water [m3]": 245802.1, "Lat": 41.879719, "Lon": -87.633362, "Weather Location Lat": 41.879719, "Weather Location Lon": -87.633362}, "84": {"Area [m2]": 3563.75, "Mean Average Height [m]": 5.08, "Electricity [GJ]": 1406.28, "Natural Gas [GJ]": 212.1, "Water [m3]": 198.99, "Lat": 41.869568, "Lon": -87.627563, "Weather Location Lat": 41.869568, "Weather Location Lon": -87.627563}, "8402": {"Area [m2]": 114271.93, "Mean Average Height [m]": 158.01, "Electricity [GJ]": 31227.26, "Natural Gas [GJ]": 25246.74, "Water [m3]": 772433.33, "Lat": 41.879719, "Lon": -87.633362, "Weather Location Lat": 41.879719, "Weather Location Lon": -87.633362}, "8403": {"Area [m2]": 72397.38, "Mean Average Height [m]": 117.64, "Electricity [GJ]": 20834.19, "Natural Gas [GJ]": 17023.34, "Water [m3]": 512492.36, "Lat": 41.8797, "Lon": -87.63678, "Weather Location Lat": 41.8797, "Weather Location Lon": -87.63678}, "8440": {"Area [m2]": 179723.14, "Mean Average Height [m]": 91.13, "Electricity [GJ]": 46899.25, "Natural Gas [GJ]": 32192.35, "Water [m3]": 1045084.03, "Lat": 41.879723, "Lon": -87.632202, "Weather Location Lat": 41.879723, "Weather Location Lon": -87.632202}, "8472": {"Area [m2]": 125306.64, "Mean Average Height [m]": 60.74, "Electricity [GJ]": 33495.38, "Natural Gas [GJ]": 22400.94, "Water [m3]": 731100.93, "Lat": 41.87973, "Lon": -87.631073, "Weather Location Lat": 41.87973, "Weather Location Lon": -87.631073}, "8487": {"Area [m2]": 214475.04, "Mean Average Height [m]": 96.6, "Electricity [GJ]": 55428.54, "Natural Gas [GJ]": 38492.58, "Water [m3]": 1237146.78, "Lat": 41.879745, "Lon": -87.628784, "Weather Location Lat": 41.879745, "Weather Location Lon": -87.628784}, "8495": {"Area [m2]": 139.96, "Mean Average Height [m]": 3.41, "Electricity [GJ]": 243.94, "Natural Gas [GJ]": 40.42, "Water [m3]": 7.82, "Lat": 41.879684000000005, "Lon": -87.637939, "Weather Location Lat": 41.879684000000005, "Weather Location Lon": -87.637939}, "8547": {"Area [m2]": 2985.71, "Mean Average Height [m]": 10.02, "Electricity [GJ]": 2370.62, "Natural Gas [GJ]": 50.17, "Water [m3]": 166.71, "Lat": 41.878914, "Lon": -87.626526, "Weather Location Lat": 41.878914, "Weather Location Lon": -87.626526}, "86": {"Area [m2]": 235.84, "Mean Average Height [m]": 3.28, "Electricity [GJ]": 287.58, "Natural Gas [GJ]": 41.08, "Water [m3]": 13.17, "Lat": 41.870365, "Lon": -87.637817, "Weather Location Lat": 41.870365, "Weather Location Lon": -87.637817}, "87": {"Area [m2]": 4034.71, "Mean Average Height [m]": 5.49, "Electricity [GJ]": 2107.26, "Natural Gas [GJ]": 136.24, "Water [m3]": 225.29, "Lat": 41.86956, "Lon": -87.62982199999999, "Weather Location Lat": 41.86956, "Weather Location Lon": -87.62982199999999}, "88": {"Area [m2]": 35991.79, "Mean Average Height [m]": 16.52, "Electricity [GJ]": 11722.9, "Natural Gas [GJ]": 2380.42, "Water [m3]": 2009.68, "Lat": 41.869568, "Lon": -87.62640400000001, "Weather Location Lat": 41.869568, "Weather Location Lon": -87.62640400000001}, "91": {"Area [m2]": 74022.45, "Mean Average Height [m]": 75.18, "Electricity [GJ]": 21011.44, "Natural Gas [GJ]": 14883.4, "Water [m3]": 467842.89, "Lat": 41.870434, "Lon": -87.625275, "Weather Location Lat": 41.870434, "Weather Location Lon": -87.625275}, "9170": {"Area [m2]": 68363.9, "Mean Average Height [m]": 72.33, "Electricity [GJ]": 19611.73, "Natural Gas [GJ]": 13866.29, "Water [m3]": 433902.98, "Lat": 41.8797, "Lon": -87.63678, "Weather Location Lat": 41.8797, "Weather Location Lon": -87.63678}, "9182": {"Area [m2]": 205939.86, "Mean Average Height [m]": 120.41, "Electricity [GJ]": 53458.92, "Natural Gas [GJ]": 38790.95, "Water [m3]": 1218669.02, "Lat": 41.8797, "Lon": -87.63678, "Weather Location Lat": 41.8797, "Weather Location Lon": -87.63678}, "9193": {"Area [m2]": 451433.65, "Mean Average Height [m]": 135.97, "Electricity [GJ]": 113547.33, "Natural Gas [GJ]": 75433.94, "Water [m3]": 2561234.33, "Lat": 41.879715000000004, "Lon": -87.634491, "Weather Location Lat": 41.879715000000004, "Weather Location Lon": -87.634491}, "92": {"Area [m2]": 10402.42, "Mean Average Height [m]": 10.73, "Electricity [GJ]": 3599.45, "Natural Gas [GJ]": 671.18, "Water [m3]": 580.84, "Lat": 41.869549, "Lon": -87.630981, "Weather Location Lat": 41.869549, "Weather Location Lon": -87.630981}, "9208": {"Area [m2]": 15686.07, "Mean Average Height [m]": 41.32, "Electricity [GJ]": 6645.97, "Natural Gas [GJ]": 3982.9, "Water [m3]": 119470.43, "Lat": 41.880565999999995, "Lon": -87.63452099999999, "Weather Location Lat": 41.880565999999995, "Weather Location Lon": -87.63452099999999}, "9225": {"Area [m2]": 83256.51, "Mean Average Height [m]": 43.86, "Electricity [GJ]": 23151.0, "Natural Gas [GJ]": 15104.19, "Water [m3]": 491287.05, "Lat": 41.879719, "Lon": -87.633362, "Weather Location Lat": 41.879719, "Weather Location Lon": -87.633362}, "9253": {"Area [m2]": 35258.34, "Mean Average Height [m]": 33.33, "Electricity [GJ]": 11382.74, "Natural Gas [GJ]": 6946.9, "Water [m3]": 225035.58, "Lat": 41.87973, "Lon": -87.631073, "Weather Location Lat": 41.87973, "Weather Location Lon": -87.631073}, "9256": {"Area [m2]": 21696.94, "Mean Average Height [m]": 25.97, "Electricity [GJ]": 8080.56, "Natural Gas [GJ]": 4571.57, "Water [m3]": 144665.93, "Lat": 41.879745, "Lon": -87.628784, "Weather Location Lat": 41.879745, "Weather Location Lon": -87.628784}, "9257": {"Area [m2]": 120683.73, "Mean Average Height [m]": 96.17, "Electricity [GJ]": 32499.72, "Natural Gas [GJ]": 23167.68, "Water [m3]": 736240.93, "Lat": 41.879745, "Lon": -87.628784, "Weather Location Lat": 41.879745, "Weather Location Lon": -87.628784}, "9259": {"Area [m2]": 78638.04, "Mean Average Height [m]": 109.45, "Electricity [GJ]": 22268.01, "Natural Gas [GJ]": 16941.4, "Water [m3]": 522693.0, "Lat": 41.879738, "Lon": -87.629944, "Weather Location Lat": 41.879738, "Weather Location Lon": -87.629944}, "9307": {"Area [m2]": 203684.76, "Mean Average Height [m]": 58.78, "Electricity [GJ]": 52694.04, "Natural Gas [GJ]": 34148.27, "Water [m3]": 1164685.24, "Lat": 41.879757, "Lon": -87.627655, "Weather Location Lat": 41.879757, "Weather Location Lon": -87.627655}, "9321": {"Area [m2]": 41400.67, "Mean Average Height [m]": 16.03, "Electricity [GJ]": 13774.75, "Natural Gas [GJ]": 2699.32, "Water [m3]": 2311.69, "Lat": 41.878918, "Lon": -87.624237, "Weather Location Lat": 41.878918, "Weather Location Lon": -87.624237}, "9325": {"Area [m2]": 149309.94, "Mean Average Height [m]": 67.37, "Electricity [GJ]": 39552.85, "Natural Gas [GJ]": 26561.98, "Water [m3]": 910006.55, "Lat": 41.879771999999996, "Lon": -87.625366, "Weather Location Lat": 41.879771999999996, "Weather Location Lon": -87.625366}, "9420": {"Area [m2]": 189.07, "Mean Average Height [m]": 3.48, "Electricity [GJ]": 275.39, "Natural Gas [GJ]": 40.55, "Water [m3]": 10.56, "Lat": 41.880581, "Lon": -87.629944, "Weather Location Lat": 41.880581, "Weather Location Lon": -87.629944}, "9535": {"Area [m2]": 1996.72, "Mean Average Height [m]": 6.34, "Electricity [GJ]": 1002.64, "Natural Gas [GJ]": 99.09, "Water [m3]": 111.49, "Lat": 41.880581, "Lon": -87.63110400000001, "Weather Location Lat": 41.880581, "Weather Location Lon": -87.63110400000001}, "9567": {"Area [m2]": 800.43, "Mean Average Height [m]": 4.8, "Electricity [GJ]": 511.14, "Natural Gas [GJ]": 54.54, "Water [m3]": 44.69, "Lat": 41.880581, "Lon": -87.629944, "Weather Location Lat": 41.880581, "Weather Location Lon": -87.629944}, "9601": {"Area [m2]": 209583.13, "Mean Average Height [m]": 123.25, "Electricity [GJ]": 54282.21, "Natural Gas [GJ]": 38434.36, "Water [m3]": 1222232.67, "Lat": 41.880547, "Lon": -87.63678, "Weather Location Lat": 41.880547, "Weather Location Lon": -87.63678}, "9604": {"Area [m2]": 7713.67, "Mean Average Height [m]": 36.85, "Electricity [GJ]": 4692.32, "Natural Gas [GJ]": 2806.33, "Water [m3]": 80155.35, "Lat": 41.880592, "Lon": -87.628815, "Weather Location Lat": 41.880592, "Weather Location Lon": -87.628815}, "9608": {"Area [m2]": 80476.08, "Mean Average Height [m]": 53.99, "Electricity [GJ]": 22594.9, "Natural Gas [GJ]": 17496.16, "Water [m3]": 499180.58, "Lat": 41.880577, "Lon": -87.632233, "Weather Location Lat": 41.880577, "Weather Location Lon": -87.632233}, "9610": {"Area [m2]": 69696.39, "Mean Average Height [m]": 95.8, "Electricity [GJ]": 20057.34, "Natural Gas [GJ]": 15136.71, "Water [m3]": 470125.8, "Lat": 41.880562, "Lon": -87.635651, "Weather Location Lat": 41.880562, "Weather Location Lon": -87.635651}, "9620": {"Area [m2]": 76241.89, "Mean Average Height [m]": 79.75, "Electricity [GJ]": 21586.47, "Natural Gas [GJ]": 15427.74, "Water [m3]": 488168.01, "Lat": 41.880565999999995, "Lon": -87.63452099999999, "Weather Location Lat": 41.880565999999995, "Weather Location Lon": -87.63452099999999}, "9623": {"Area [m2]": 75559.13, "Mean Average Height [m]": 54.18, "Electricity [GJ]": 21308.63, "Natural Gas [GJ]": 14154.91, "Water [m3]": 458587.28, "Lat": 41.880569, "Lon": -87.633362, "Weather Location Lat": 41.880569, "Weather Location Lon": -87.633362}, "9625": {"Area [m2]": 20465.59, "Mean Average Height [m]": 62.4, "Electricity [GJ]": 7953.45, "Natural Gas [GJ]": 5971.01, "Water [m3]": 176996.91, "Lat": 41.880592, "Lon": -87.628815, "Weather Location Lat": 41.880592, "Weather Location Lon": -87.628815}, "9655": {"Area [m2]": 21747.44, "Mean Average Height [m]": 43.73, "Electricity [GJ]": 8187.78, "Natural Gas [GJ]": 5419.9, "Water [m3]": 166161.3, "Lat": 41.880592, "Lon": -87.628815, "Weather Location Lat": 41.880592, "Weather Location Lon": -87.628815}, "9776": {"Area [m2]": 46534.27, "Mean Average Height [m]": 106.63, "Electricity [GJ]": 14405.62, "Natural Gas [GJ]": 12015.66, "Water [m3]": 348445.31, "Lat": 41.881428, "Lon": -87.63110400000001, "Weather Location Lat": 41.881428, "Weather Location Lon": -87.63110400000001}, "99": {"Area [m2]": 605.45, "Mean Average Height [m]": 3.66, "Electricity [GJ]": 461.54, "Natural Gas [GJ]": 46.81, "Water [m3]": 33.81, "Lat": 41.870373, "Lon": -87.636688, "Weather Location Lat": 41.870373, "Weather Location Lon": -87.636688}, "9923": {"Area [m2]": 128864.61, "Mean Average Height [m]": 78.23, "Electricity [GJ]": 34513.83, "Natural Gas [GJ]": 23603.0, "Water [m3]": 787734.72, "Lat": 41.880615, "Lon": -87.62539699999999, "Weather Location Lat": 41.880615, "Weather Location Lon": -87.62539699999999}}